<?xml version="1.0" encoding="utf-8"?>
<cal_revenues><meta><autoIncrement>13</autoIncrement></meta><data><row><id>1</id><FR_2012>0</FR_2012><OI_2012>0</OI_2012><TOI_2012>0</TOI_2012><FR_2013>0</FR_2013><OI_2013>0</OI_2013><TOI_2013>0</TOI_2013><FR_2014>0</FR_2014><OI_2014>0</OI_2014><TOI_2014>0</TOI_2014><FR_2015>0</FR_2015><OI_2015>0</OI_2015><TOI_2015>0</TOI_2015><FR_2016>0</FR_2016><OI_2016>0</OI_2016><TOI_2016>0</TOI_2016><FR_2017>0</FR_2017><OI_2017>0</OI_2017><TOI_2017>0</TOI_2017><FR_2018>0</FR_2018><OI_2018>0</OI_2018><TOI_2018>0</TOI_2018><FR_2019>0</FR_2019><OI_2019>0</OI_2019><TOI_2019>0</TOI_2019><FR_2020>0</FR_2020><OI_2020>0</OI_2020><TOI_2020>0</TOI_2020><FR_2021>0</FR_2021><OI_2021>0</OI_2021><TOI_2021>0</TOI_2021><FR_2022>0</FR_2022><OI_2022>0</OI_2022><TOI_2022>0</TOI_2022><FR_2023>0</FR_2023><OI_2023>0</OI_2023><TOI_2023>0</TOI_2023><FR_2024>0</FR_2024><OI_2024>0</OI_2024><TOI_2024>0</TOI_2024><FR_2025>0</FR_2025><OI_2025>0</OI_2025><TOI_2025>0</TOI_2025><FR_2026>0</FR_2026><OI_2026>0</OI_2026><TOI_2026>0</TOI_2026><FR_2027>0</FR_2027><OI_2027>0</OI_2027><TOI_2027>0</TOI_2027><FR_2028>0</FR_2028><OI_2028>0</OI_2028><TOI_2028>0</TOI_2028><FR_2029>0</FR_2029><OI_2029>0</OI_2029><TOI_2029>0</TOI_2029><FR_2030>0</FR_2030><OI_2030>0</OI_2030><TOI_2030>0</TOI_2030><FR_2031>0</FR_2031><OI_2031>0</OI_2031><TOI_2031>0</TOI_2031><FR_2032>0</FR_2032><OI_2032>0</OI_2032><TOI_2032>0</TOI_2032><FR_2033>0</FR_2033><OI_2033>0</OI_2033><TOI_2033>0</TOI_2033><FR_2034>0</FR_2034><OI_2034>0</OI_2034><TOI_2034>0</TOI_2034><FR_2035>0</FR_2035><OI_2035>0</OI_2035><TOI_2035>0</TOI_2035><FR_2036>0</FR_2036><OI_2036>0</OI_2036><TOI_2036>0</TOI_2036><FR_2037>0</FR_2037><OI_2037>0</OI_2037><TOI_2037>0</TOI_2037><FR_2038>0</FR_2038><OI_2038>0</OI_2038><TOI_2038>0</TOI_2038><FR_2039>0</FR_2039><OI_2039>0</OI_2039><TOI_2039>0</TOI_2039><FR_2040>0</FR_2040><OI_2040>0</OI_2040><TOI_2040>0</TOI_2040><FR_2041>0</FR_2041><OI_2041>0</OI_2041><TOI_2041>0</TOI_2041><FR_2042>0</FR_2042><OI_2042>0</OI_2042><TOI_2042>0</TOI_2042><FR_2043>0</FR_2043><OI_2043>0</OI_2043><TOI_2043>0</TOI_2043><FR_2044>0</FR_2044><OI_2044>0</OI_2044><TOI_2044>0</TOI_2044><FR_2045>0</FR_2045><OI_2045>0</OI_2045><TOI_2045>0</TOI_2045><sid>1</sid></row><row><id>2</id><FR_2012>9.72</FR_2012><OI_2012>7.42</OI_2012><TOI_2012>17.14</TOI_2012><FR_2013>10.4976</FR_2013><OI_2013>7.8652</OI_2013><TOI_2013>18.3628</TOI_2013><FR_2014>11.337408</FR_2014><OI_2014>8.337112</OI_2014><TOI_2014>19.67452</TOI_2014><FR_2015>12.24440064</FR_2015><OI_2015>8.83733872</OI_2015><TOI_2015>21.08173936</TOI_2015><FR_2016>13.2239526912</FR_2016><OI_2016>9.3675790432</OI_2016><TOI_2016>22.5915317344</TOI_2016><FR_2017>14.281868906496</FR_2017><OI_2017>9.929633785792</OI_2017><TOI_2017>24.211502692288</TOI_2017><FR_2018>15.424418419016</FR_2018><OI_2018>10.52541181294</OI_2018><TOI_2018>25.949830231955</TOI_2018><FR_2019>16.658371892537</FR_2019><OI_2019>11.156936521716</OI_2019><TOI_2019>27.815308414253</TOI_2019><FR_2020>17.99104164394</FR_2020><OI_2020>11.826352713019</OI_2020><TOI_2020>29.817394356959</TOI_2020><FR_2021>19.430324975455</FR_2021><OI_2021>12.5359338758</OI_2021><TOI_2021>31.966258851255</TOI_2021><FR_2022>20.984750973492</FR_2022><OI_2022>13.288089908348</OI_2022><TOI_2022>34.272840881839</TOI_2022><FR_2023>22.663531051371</FR_2023><OI_2023>14.085375302849</OI_2023><TOI_2023>36.74890635422</TOI_2023><FR_2024>24.47661353548</FR_2024><OI_2024>14.93049782102</OI_2024><TOI_2024>39.4071113565</TOI_2024><FR_2025>26.434742618319</FR_2025><OI_2025>15.826327690281</OI_2025><TOI_2025>42.2610703086</TOI_2025><FR_2026>28.549522027784</FR_2026><OI_2026>16.775907351698</OI_2026><TOI_2026>45.325429379482</TOI_2026><FR_2027>30.833483790007</FR_2027><OI_2027>17.7824617928</OI_2027><TOI_2027>48.615945582807</TOI_2027><FR_2028>33.300162493208</FR_2028><OI_2028>18.849409500368</OI_2028><TOI_2028>52.149571993575</TOI_2028><FR_2029>35.964175492664</FR_2029><OI_2029>19.98037407039</OI_2029><TOI_2029>55.944549563054</TOI_2029><FR_2030>38.841309532078</FR_2030><OI_2030>21.179196514613</OI_2030><TOI_2030>60.020506046691</TOI_2030><FR_2031>41.948614294644</FR_2031><OI_2031>22.44994830549</OI_2031><TOI_2031>64.398562600134</TOI_2031><FR_2032>45.304503438215</FR_2032><OI_2032>23.796945203819</OI_2032><TOI_2032>69.101448642035</TOI_2032><FR_2033>48.928863713272</FR_2033><OI_2033>25.224761916048</OI_2033><TOI_2033>74.153625629321</TOI_2033><FR_2034>52.843172810334</FR_2034><OI_2034>26.738247631011</OI_2034><TOI_2034>79.581420441346</TOI_2034><FR_2035>57.070626635161</FR_2035><OI_2035>28.342542488872</OI_2035><TOI_2035>85.413169124033</TOI_2035><FR_2036>61.636276765974</FR_2036><OI_2036>30.043095038204</OI_2036><TOI_2036>91.679371804178</TOI_2036><FR_2037>66.567178907252</FR_2037><OI_2037>31.845680740497</OI_2037><TOI_2037>98.412859647749</TOI_2037><FR_2038>71.892553219832</FR_2038><OI_2038>33.756421584926</OI_2038><TOI_2038>105.64897480476</TOI_2038><FR_2039>77.643957477419</FR_2039><OI_2039>35.781806880022</OI_2039><TOI_2039>113.42576435744</TOI_2039><FR_2040>83.855474075612</FR_2040><OI_2040>37.928715292823</OI_2040><TOI_2040>121.78418936844</TOI_2040><FR_2041>90.563912001661</FR_2041><OI_2041>40.204438210393</OI_2041><TOI_2041>130.76835021205</TOI_2041><FR_2042>97.809024961794</FR_2042><OI_2042>42.616704503016</OI_2042><TOI_2042>140.42572946481</TOI_2042><FR_2043>105.63374695874</FR_2043><OI_2043>45.173706773197</OI_2043><TOI_2043>150.80745373193</TOI_2043><FR_2044>114.08444671544</FR_2044><OI_2044>47.884129179589</OI_2044><TOI_2044>161.96857589503</TOI_2044><FR_2045>123.21120245267</FR_2045><OI_2045>50.757176930365</OI_2045><TOI_2045>173.96837938304</TOI_2045><sid>1</sid></row><row><id>3</id><FR_2012>9.72</FR_2012><OI_2012>7.42</OI_2012><TOI_2012>17.14</TOI_2012><FR_2013>10.4976</FR_2013><OI_2013>7.8652</OI_2013><TOI_2013>18.3628</TOI_2013><FR_2014>11.337408</FR_2014><OI_2014>8.337112</OI_2014><TOI_2014>19.67452</TOI_2014><FR_2015>12.24440064</FR_2015><OI_2015>8.83733872</OI_2015><TOI_2015>21.08173936</TOI_2015><FR_2016>13.2239526912</FR_2016><OI_2016>9.3675790432</OI_2016><TOI_2016>22.5915317344</TOI_2016><FR_2017>14.281868906496</FR_2017><OI_2017>9.929633785792</OI_2017><TOI_2017>24.211502692288</TOI_2017><FR_2018>15.424418419016</FR_2018><OI_2018>10.52541181294</OI_2018><TOI_2018>25.949830231955</TOI_2018><FR_2019>16.658371892537</FR_2019><OI_2019>11.156936521716</OI_2019><TOI_2019>27.815308414253</TOI_2019><FR_2020>17.99104164394</FR_2020><OI_2020>11.826352713019</OI_2020><TOI_2020>29.817394356959</TOI_2020><FR_2021>19.430324975455</FR_2021><OI_2021>12.5359338758</OI_2021><TOI_2021>31.966258851255</TOI_2021><FR_2022>20.984750973492</FR_2022><OI_2022>13.288089908348</OI_2022><TOI_2022>34.272840881839</TOI_2022><FR_2023>22.663531051371</FR_2023><OI_2023>14.085375302849</OI_2023><TOI_2023>36.74890635422</TOI_2023><FR_2024>24.47661353548</FR_2024><OI_2024>14.93049782102</OI_2024><TOI_2024>39.4071113565</TOI_2024><FR_2025>26.434742618319</FR_2025><OI_2025>15.826327690281</OI_2025><TOI_2025>42.2610703086</TOI_2025><FR_2026>28.549522027784</FR_2026><OI_2026>16.775907351698</OI_2026><TOI_2026>45.325429379482</TOI_2026><FR_2027>30.833483790007</FR_2027><OI_2027>17.7824617928</OI_2027><TOI_2027>48.615945582807</TOI_2027><FR_2028>33.300162493208</FR_2028><OI_2028>18.849409500368</OI_2028><TOI_2028>52.149571993575</TOI_2028><FR_2029>35.964175492664</FR_2029><OI_2029>19.98037407039</OI_2029><TOI_2029>55.944549563054</TOI_2029><FR_2030>38.841309532078</FR_2030><OI_2030>21.179196514613</OI_2030><TOI_2030>60.020506046691</TOI_2030><FR_2031>41.948614294644</FR_2031><OI_2031>22.44994830549</OI_2031><TOI_2031>64.398562600134</TOI_2031><FR_2032>45.304503438215</FR_2032><OI_2032>23.796945203819</OI_2032><TOI_2032>69.101448642035</TOI_2032><FR_2033>48.928863713272</FR_2033><OI_2033>25.224761916048</OI_2033><TOI_2033>74.153625629321</TOI_2033><FR_2034>52.843172810334</FR_2034><OI_2034>26.738247631011</OI_2034><TOI_2034>79.581420441346</TOI_2034><FR_2035>57.070626635161</FR_2035><OI_2035>28.342542488872</OI_2035><TOI_2035>85.413169124033</TOI_2035><FR_2036>61.636276765974</FR_2036><OI_2036>30.043095038204</OI_2036><TOI_2036>91.679371804178</TOI_2036><FR_2037>66.567178907252</FR_2037><OI_2037>31.845680740497</OI_2037><TOI_2037>98.412859647749</TOI_2037><FR_2038>71.892553219832</FR_2038><OI_2038>33.756421584926</OI_2038><TOI_2038>105.64897480476</TOI_2038><FR_2039>77.643957477419</FR_2039><OI_2039>35.781806880022</OI_2039><TOI_2039>113.42576435744</TOI_2039><FR_2040>83.855474075612</FR_2040><OI_2040>37.928715292823</OI_2040><TOI_2040>121.78418936844</TOI_2040><FR_2041>90.563912001661</FR_2041><OI_2041>40.204438210393</OI_2041><TOI_2041>130.76835021205</TOI_2041><FR_2042>97.809024961794</FR_2042><OI_2042>42.616704503016</OI_2042><TOI_2042>140.42572946481</TOI_2042><FR_2043>105.63374695874</FR_2043><OI_2043>45.173706773197</OI_2043><TOI_2043>150.80745373193</TOI_2043><FR_2044>114.08444671544</FR_2044><OI_2044>47.884129179589</OI_2044><TOI_2044>161.96857589503</TOI_2044><FR_2045>123.21120245267</FR_2045><OI_2045>50.757176930365</OI_2045><TOI_2045>173.96837938304</TOI_2045><sid>1</sid></row><row><id>4</id><FR_2012>9.72</FR_2012><OI_2012>7.42</OI_2012><TOI_2012>17.14</TOI_2012><FR_2013>10.4976</FR_2013><OI_2013>7.8652</OI_2013><TOI_2013>18.3628</TOI_2013><FR_2014>11.337408</FR_2014><OI_2014>8.337112</OI_2014><TOI_2014>19.67452</TOI_2014><FR_2015>12.24440064</FR_2015><OI_2015>8.83733872</OI_2015><TOI_2015>21.08173936</TOI_2015><FR_2016>13.2239526912</FR_2016><OI_2016>9.3675790432</OI_2016><TOI_2016>22.5915317344</TOI_2016><FR_2017>14.281868906496</FR_2017><OI_2017>9.929633785792</OI_2017><TOI_2017>24.211502692288</TOI_2017><FR_2018>15.424418419016</FR_2018><OI_2018>10.52541181294</OI_2018><TOI_2018>25.949830231955</TOI_2018><FR_2019>16.658371892537</FR_2019><OI_2019>11.156936521716</OI_2019><TOI_2019>27.815308414253</TOI_2019><FR_2020>17.99104164394</FR_2020><OI_2020>11.826352713019</OI_2020><TOI_2020>29.817394356959</TOI_2020><FR_2021>19.430324975455</FR_2021><OI_2021>12.5359338758</OI_2021><TOI_2021>31.966258851255</TOI_2021><FR_2022>20.984750973492</FR_2022><OI_2022>13.288089908348</OI_2022><TOI_2022>34.272840881839</TOI_2022><FR_2023>22.663531051371</FR_2023><OI_2023>14.085375302849</OI_2023><TOI_2023>36.74890635422</TOI_2023><FR_2024>24.47661353548</FR_2024><OI_2024>14.93049782102</OI_2024><TOI_2024>39.4071113565</TOI_2024><FR_2025>26.434742618319</FR_2025><OI_2025>15.826327690281</OI_2025><TOI_2025>42.2610703086</TOI_2025><FR_2026>28.549522027784</FR_2026><OI_2026>16.775907351698</OI_2026><TOI_2026>45.325429379482</TOI_2026><FR_2027>30.833483790007</FR_2027><OI_2027>17.7824617928</OI_2027><TOI_2027>48.615945582807</TOI_2027><FR_2028>33.300162493208</FR_2028><OI_2028>18.849409500368</OI_2028><TOI_2028>52.149571993575</TOI_2028><FR_2029>35.964175492664</FR_2029><OI_2029>19.98037407039</OI_2029><TOI_2029>55.944549563054</TOI_2029><FR_2030>38.841309532078</FR_2030><OI_2030>21.179196514613</OI_2030><TOI_2030>60.020506046691</TOI_2030><FR_2031>41.948614294644</FR_2031><OI_2031>22.44994830549</OI_2031><TOI_2031>64.398562600134</TOI_2031><FR_2032>45.304503438215</FR_2032><OI_2032>23.796945203819</OI_2032><TOI_2032>69.101448642035</TOI_2032><FR_2033>48.928863713272</FR_2033><OI_2033>25.224761916048</OI_2033><TOI_2033>74.153625629321</TOI_2033><FR_2034>52.843172810334</FR_2034><OI_2034>26.738247631011</OI_2034><TOI_2034>79.581420441346</TOI_2034><FR_2035>57.070626635161</FR_2035><OI_2035>28.342542488872</OI_2035><TOI_2035>85.413169124033</TOI_2035><FR_2036>61.636276765974</FR_2036><OI_2036>30.043095038204</OI_2036><TOI_2036>91.679371804178</TOI_2036><FR_2037>66.567178907252</FR_2037><OI_2037>31.845680740497</OI_2037><TOI_2037>98.412859647749</TOI_2037><FR_2038>71.892553219832</FR_2038><OI_2038>33.756421584926</OI_2038><TOI_2038>105.64897480476</TOI_2038><FR_2039>77.643957477419</FR_2039><OI_2039>35.781806880022</OI_2039><TOI_2039>113.42576435744</TOI_2039><FR_2040>83.855474075612</FR_2040><OI_2040>37.928715292823</OI_2040><TOI_2040>121.78418936844</TOI_2040><FR_2041>90.563912001661</FR_2041><OI_2041>40.204438210393</OI_2041><TOI_2041>130.76835021205</TOI_2041><FR_2042>97.809024961794</FR_2042><OI_2042>42.616704503016</OI_2042><TOI_2042>140.42572946481</TOI_2042><FR_2043>105.63374695874</FR_2043><OI_2043>45.173706773197</OI_2043><TOI_2043>150.80745373193</TOI_2043><FR_2044>114.08444671544</FR_2044><OI_2044>47.884129179589</OI_2044><TOI_2044>161.96857589503</TOI_2044><FR_2045>123.21120245267</FR_2045><OI_2045>50.757176930365</OI_2045><TOI_2045>173.96837938304</TOI_2045><sid>1</sid></row><row><id>5</id><FR_2012>9.72</FR_2012><OI_2012>7.42</OI_2012><TOI_2012>17.14</TOI_2012><FR_2013>10.4976</FR_2013><OI_2013>7.8652</OI_2013><TOI_2013>18.3628</TOI_2013><FR_2014>11.337408</FR_2014><OI_2014>8.337112</OI_2014><TOI_2014>19.67452</TOI_2014><FR_2015>12.24440064</FR_2015><OI_2015>8.83733872</OI_2015><TOI_2015>21.08173936</TOI_2015><FR_2016>13.2239526912</FR_2016><OI_2016>9.3675790432</OI_2016><TOI_2016>22.5915317344</TOI_2016><FR_2017>14.281868906496</FR_2017><OI_2017>9.929633785792</OI_2017><TOI_2017>24.211502692288</TOI_2017><FR_2018>15.424418419016</FR_2018><OI_2018>10.52541181294</OI_2018><TOI_2018>25.949830231955</TOI_2018><FR_2019>16.658371892537</FR_2019><OI_2019>11.156936521716</OI_2019><TOI_2019>27.815308414253</TOI_2019><FR_2020>17.99104164394</FR_2020><OI_2020>11.826352713019</OI_2020><TOI_2020>29.817394356959</TOI_2020><FR_2021>19.430324975455</FR_2021><OI_2021>12.5359338758</OI_2021><TOI_2021>31.966258851255</TOI_2021><FR_2022>20.984750973492</FR_2022><OI_2022>13.288089908348</OI_2022><TOI_2022>34.272840881839</TOI_2022><FR_2023>22.663531051371</FR_2023><OI_2023>14.085375302849</OI_2023><TOI_2023>36.74890635422</TOI_2023><FR_2024>24.47661353548</FR_2024><OI_2024>14.93049782102</OI_2024><TOI_2024>39.4071113565</TOI_2024><FR_2025>26.434742618319</FR_2025><OI_2025>15.826327690281</OI_2025><TOI_2025>42.2610703086</TOI_2025><FR_2026>28.549522027784</FR_2026><OI_2026>16.775907351698</OI_2026><TOI_2026>45.325429379482</TOI_2026><FR_2027>30.833483790007</FR_2027><OI_2027>17.7824617928</OI_2027><TOI_2027>48.615945582807</TOI_2027><FR_2028>33.300162493208</FR_2028><OI_2028>18.849409500368</OI_2028><TOI_2028>52.149571993575</TOI_2028><FR_2029>35.964175492664</FR_2029><OI_2029>19.98037407039</OI_2029><TOI_2029>55.944549563054</TOI_2029><FR_2030>38.841309532078</FR_2030><OI_2030>21.179196514613</OI_2030><TOI_2030>60.020506046691</TOI_2030><FR_2031>41.948614294644</FR_2031><OI_2031>22.44994830549</OI_2031><TOI_2031>64.398562600134</TOI_2031><FR_2032>45.304503438215</FR_2032><OI_2032>23.796945203819</OI_2032><TOI_2032>69.101448642035</TOI_2032><FR_2033>48.928863713272</FR_2033><OI_2033>25.224761916048</OI_2033><TOI_2033>74.153625629321</TOI_2033><FR_2034>52.843172810334</FR_2034><OI_2034>26.738247631011</OI_2034><TOI_2034>79.581420441346</TOI_2034><FR_2035>57.070626635161</FR_2035><OI_2035>28.342542488872</OI_2035><TOI_2035>85.413169124033</TOI_2035><FR_2036>61.636276765974</FR_2036><OI_2036>30.043095038204</OI_2036><TOI_2036>91.679371804178</TOI_2036><FR_2037>66.567178907252</FR_2037><OI_2037>31.845680740497</OI_2037><TOI_2037>98.412859647749</TOI_2037><FR_2038>71.892553219832</FR_2038><OI_2038>33.756421584926</OI_2038><TOI_2038>105.64897480476</TOI_2038><FR_2039>77.643957477419</FR_2039><OI_2039>35.781806880022</OI_2039><TOI_2039>113.42576435744</TOI_2039><FR_2040>83.855474075612</FR_2040><OI_2040>37.928715292823</OI_2040><TOI_2040>121.78418936844</TOI_2040><FR_2041>90.563912001661</FR_2041><OI_2041>40.204438210393</OI_2041><TOI_2041>130.76835021205</TOI_2041><FR_2042>97.809024961794</FR_2042><OI_2042>42.616704503016</OI_2042><TOI_2042>140.42572946481</TOI_2042><FR_2043>105.63374695874</FR_2043><OI_2043>45.173706773197</OI_2043><TOI_2043>150.80745373193</TOI_2043><FR_2044>114.08444671544</FR_2044><OI_2044>47.884129179589</OI_2044><TOI_2044>161.96857589503</TOI_2044><FR_2045>123.21120245267</FR_2045><OI_2045>50.757176930365</OI_2045><TOI_2045>173.96837938304</TOI_2045><sid>1</sid></row><row><id>6</id><FR_2012>9.72</FR_2012><OI_2012>7.42</OI_2012><TOI_2012>17.14</TOI_2012><FR_2013>10.4976</FR_2013><OI_2013>7.8652</OI_2013><TOI_2013>18.3628</TOI_2013><FR_2014>11.337408</FR_2014><OI_2014>8.337112</OI_2014><TOI_2014>19.67452</TOI_2014><FR_2015>12.24440064</FR_2015><OI_2015>8.83733872</OI_2015><TOI_2015>21.08173936</TOI_2015><FR_2016>13.2239526912</FR_2016><OI_2016>9.3675790432</OI_2016><TOI_2016>22.5915317344</TOI_2016><FR_2017>14.281868906496</FR_2017><OI_2017>9.929633785792</OI_2017><TOI_2017>24.211502692288</TOI_2017><FR_2018>15.424418419016</FR_2018><OI_2018>10.52541181294</OI_2018><TOI_2018>25.949830231955</TOI_2018><FR_2019>16.658371892537</FR_2019><OI_2019>11.156936521716</OI_2019><TOI_2019>27.815308414253</TOI_2019><FR_2020>17.99104164394</FR_2020><OI_2020>11.826352713019</OI_2020><TOI_2020>29.817394356959</TOI_2020><FR_2021>19.430324975455</FR_2021><OI_2021>12.5359338758</OI_2021><TOI_2021>31.966258851255</TOI_2021><FR_2022>20.984750973492</FR_2022><OI_2022>13.288089908348</OI_2022><TOI_2022>34.272840881839</TOI_2022><FR_2023>22.663531051371</FR_2023><OI_2023>14.085375302849</OI_2023><TOI_2023>36.74890635422</TOI_2023><FR_2024>24.47661353548</FR_2024><OI_2024>14.93049782102</OI_2024><TOI_2024>39.4071113565</TOI_2024><FR_2025>26.434742618319</FR_2025><OI_2025>15.826327690281</OI_2025><TOI_2025>42.2610703086</TOI_2025><FR_2026>28.549522027784</FR_2026><OI_2026>16.775907351698</OI_2026><TOI_2026>45.325429379482</TOI_2026><FR_2027>30.833483790007</FR_2027><OI_2027>17.7824617928</OI_2027><TOI_2027>48.615945582807</TOI_2027><FR_2028>33.300162493208</FR_2028><OI_2028>18.849409500368</OI_2028><TOI_2028>52.149571993575</TOI_2028><FR_2029>35.964175492664</FR_2029><OI_2029>19.98037407039</OI_2029><TOI_2029>55.944549563054</TOI_2029><FR_2030>38.841309532078</FR_2030><OI_2030>21.179196514613</OI_2030><TOI_2030>60.020506046691</TOI_2030><FR_2031>41.948614294644</FR_2031><OI_2031>22.44994830549</OI_2031><TOI_2031>64.398562600134</TOI_2031><FR_2032>45.304503438215</FR_2032><OI_2032>23.796945203819</OI_2032><TOI_2032>69.101448642035</TOI_2032><FR_2033>48.928863713272</FR_2033><OI_2033>25.224761916048</OI_2033><TOI_2033>74.153625629321</TOI_2033><FR_2034>52.843172810334</FR_2034><OI_2034>26.738247631011</OI_2034><TOI_2034>79.581420441346</TOI_2034><FR_2035>57.070626635161</FR_2035><OI_2035>28.342542488872</OI_2035><TOI_2035>85.413169124033</TOI_2035><FR_2036>61.636276765974</FR_2036><OI_2036>30.043095038204</OI_2036><TOI_2036>91.679371804178</TOI_2036><FR_2037>66.567178907252</FR_2037><OI_2037>31.845680740497</OI_2037><TOI_2037>98.412859647749</TOI_2037><FR_2038>71.892553219832</FR_2038><OI_2038>33.756421584926</OI_2038><TOI_2038>105.64897480476</TOI_2038><FR_2039>77.643957477419</FR_2039><OI_2039>35.781806880022</OI_2039><TOI_2039>113.42576435744</TOI_2039><FR_2040>83.855474075612</FR_2040><OI_2040>37.928715292823</OI_2040><TOI_2040>121.78418936844</TOI_2040><FR_2041>90.563912001661</FR_2041><OI_2041>40.204438210393</OI_2041><TOI_2041>130.76835021205</TOI_2041><FR_2042>97.809024961794</FR_2042><OI_2042>42.616704503016</OI_2042><TOI_2042>140.42572946481</TOI_2042><FR_2043>105.63374695874</FR_2043><OI_2043>45.173706773197</OI_2043><TOI_2043>150.80745373193</TOI_2043><FR_2044>114.08444671544</FR_2044><OI_2044>47.884129179589</OI_2044><TOI_2044>161.96857589503</TOI_2044><FR_2045>123.21120245267</FR_2045><OI_2045>50.757176930365</OI_2045><TOI_2045>173.96837938304</TOI_2045><sid>1</sid></row><row><id>7</id><FR_2012>9.72</FR_2012><OI_2012>7.42</OI_2012><TOI_2012>17.14</TOI_2012><FR_2013>10.4976</FR_2013><OI_2013>7.8652</OI_2013><TOI_2013>18.3628</TOI_2013><FR_2014>11.337408</FR_2014><OI_2014>8.337112</OI_2014><TOI_2014>19.67452</TOI_2014><FR_2015>12.24440064</FR_2015><OI_2015>8.83733872</OI_2015><TOI_2015>21.08173936</TOI_2015><FR_2016>13.2239526912</FR_2016><OI_2016>9.3675790432</OI_2016><TOI_2016>22.5915317344</TOI_2016><FR_2017>14.281868906496</FR_2017><OI_2017>9.929633785792</OI_2017><TOI_2017>24.211502692288</TOI_2017><FR_2018>15.424418419016</FR_2018><OI_2018>10.52541181294</OI_2018><TOI_2018>25.949830231955</TOI_2018><FR_2019>16.658371892537</FR_2019><OI_2019>11.156936521716</OI_2019><TOI_2019>27.815308414253</TOI_2019><FR_2020>17.99104164394</FR_2020><OI_2020>11.826352713019</OI_2020><TOI_2020>29.817394356959</TOI_2020><FR_2021>19.430324975455</FR_2021><OI_2021>12.5359338758</OI_2021><TOI_2021>31.966258851255</TOI_2021><FR_2022>20.984750973492</FR_2022><OI_2022>13.288089908348</OI_2022><TOI_2022>34.272840881839</TOI_2022><FR_2023>22.663531051371</FR_2023><OI_2023>14.085375302849</OI_2023><TOI_2023>36.74890635422</TOI_2023><FR_2024>24.47661353548</FR_2024><OI_2024>14.93049782102</OI_2024><TOI_2024>39.4071113565</TOI_2024><FR_2025>26.434742618319</FR_2025><OI_2025>15.826327690281</OI_2025><TOI_2025>42.2610703086</TOI_2025><FR_2026>28.549522027784</FR_2026><OI_2026>16.775907351698</OI_2026><TOI_2026>45.325429379482</TOI_2026><FR_2027>30.833483790007</FR_2027><OI_2027>17.7824617928</OI_2027><TOI_2027>48.615945582807</TOI_2027><FR_2028>33.300162493208</FR_2028><OI_2028>18.849409500368</OI_2028><TOI_2028>52.149571993575</TOI_2028><FR_2029>35.964175492664</FR_2029><OI_2029>19.98037407039</OI_2029><TOI_2029>55.944549563054</TOI_2029><FR_2030>38.841309532078</FR_2030><OI_2030>21.179196514613</OI_2030><TOI_2030>60.020506046691</TOI_2030><FR_2031>41.948614294644</FR_2031><OI_2031>22.44994830549</OI_2031><TOI_2031>64.398562600134</TOI_2031><FR_2032>45.304503438215</FR_2032><OI_2032>23.796945203819</OI_2032><TOI_2032>69.101448642035</TOI_2032><FR_2033>48.928863713272</FR_2033><OI_2033>25.224761916048</OI_2033><TOI_2033>74.153625629321</TOI_2033><FR_2034>52.843172810334</FR_2034><OI_2034>26.738247631011</OI_2034><TOI_2034>79.581420441346</TOI_2034><FR_2035>57.070626635161</FR_2035><OI_2035>28.342542488872</OI_2035><TOI_2035>85.413169124033</TOI_2035><FR_2036>61.636276765974</FR_2036><OI_2036>30.043095038204</OI_2036><TOI_2036>91.679371804178</TOI_2036><FR_2037>66.567178907252</FR_2037><OI_2037>31.845680740497</OI_2037><TOI_2037>98.412859647749</TOI_2037><FR_2038>71.892553219832</FR_2038><OI_2038>33.756421584926</OI_2038><TOI_2038>105.64897480476</TOI_2038><FR_2039>77.643957477419</FR_2039><OI_2039>35.781806880022</OI_2039><TOI_2039>113.42576435744</TOI_2039><FR_2040>83.855474075612</FR_2040><OI_2040>37.928715292823</OI_2040><TOI_2040>121.78418936844</TOI_2040><FR_2041>90.563912001661</FR_2041><OI_2041>40.204438210393</OI_2041><TOI_2041>130.76835021205</TOI_2041><FR_2042>97.809024961794</FR_2042><OI_2042>42.616704503016</OI_2042><TOI_2042>140.42572946481</TOI_2042><FR_2043>105.63374695874</FR_2043><OI_2043>45.173706773197</OI_2043><TOI_2043>150.80745373193</TOI_2043><FR_2044>114.08444671544</FR_2044><OI_2044>47.884129179589</OI_2044><TOI_2044>161.96857589503</TOI_2044><FR_2045>123.21120245267</FR_2045><OI_2045>50.757176930365</OI_2045><TOI_2045>173.96837938304</TOI_2045><sid>1</sid></row><row><id>8</id><FR_2012>9.72</FR_2012><OI_2012>7.42</OI_2012><TOI_2012>17.14</TOI_2012><FR_2013>10.4976</FR_2013><OI_2013>7.8652</OI_2013><TOI_2013>18.3628</TOI_2013><FR_2014>11.337408</FR_2014><OI_2014>8.337112</OI_2014><TOI_2014>19.67452</TOI_2014><FR_2015>12.24440064</FR_2015><OI_2015>8.83733872</OI_2015><TOI_2015>21.08173936</TOI_2015><FR_2016>13.2239526912</FR_2016><OI_2016>9.3675790432</OI_2016><TOI_2016>22.5915317344</TOI_2016><FR_2017>14.281868906496</FR_2017><OI_2017>9.929633785792</OI_2017><TOI_2017>24.211502692288</TOI_2017><FR_2018>15.424418419016</FR_2018><OI_2018>10.52541181294</OI_2018><TOI_2018>25.949830231955</TOI_2018><FR_2019>16.658371892537</FR_2019><OI_2019>11.156936521716</OI_2019><TOI_2019>27.815308414253</TOI_2019><FR_2020>17.99104164394</FR_2020><OI_2020>11.826352713019</OI_2020><TOI_2020>29.817394356959</TOI_2020><FR_2021>19.430324975455</FR_2021><OI_2021>12.5359338758</OI_2021><TOI_2021>31.966258851255</TOI_2021><FR_2022>20.984750973492</FR_2022><OI_2022>13.288089908348</OI_2022><TOI_2022>34.272840881839</TOI_2022><FR_2023>22.663531051371</FR_2023><OI_2023>14.085375302849</OI_2023><TOI_2023>36.74890635422</TOI_2023><FR_2024>24.47661353548</FR_2024><OI_2024>14.93049782102</OI_2024><TOI_2024>39.4071113565</TOI_2024><FR_2025>26.434742618319</FR_2025><OI_2025>15.826327690281</OI_2025><TOI_2025>42.2610703086</TOI_2025><FR_2026>28.549522027784</FR_2026><OI_2026>16.775907351698</OI_2026><TOI_2026>45.325429379482</TOI_2026><FR_2027>30.833483790007</FR_2027><OI_2027>17.7824617928</OI_2027><TOI_2027>48.615945582807</TOI_2027><FR_2028>33.300162493208</FR_2028><OI_2028>18.849409500368</OI_2028><TOI_2028>52.149571993575</TOI_2028><FR_2029>35.964175492664</FR_2029><OI_2029>19.98037407039</OI_2029><TOI_2029>55.944549563054</TOI_2029><FR_2030>38.841309532078</FR_2030><OI_2030>21.179196514613</OI_2030><TOI_2030>60.020506046691</TOI_2030><FR_2031>41.948614294644</FR_2031><OI_2031>22.44994830549</OI_2031><TOI_2031>64.398562600134</TOI_2031><FR_2032>45.304503438215</FR_2032><OI_2032>23.796945203819</OI_2032><TOI_2032>69.101448642035</TOI_2032><FR_2033>48.928863713272</FR_2033><OI_2033>25.224761916048</OI_2033><TOI_2033>74.153625629321</TOI_2033><FR_2034>52.843172810334</FR_2034><OI_2034>26.738247631011</OI_2034><TOI_2034>79.581420441346</TOI_2034><FR_2035>57.070626635161</FR_2035><OI_2035>28.342542488872</OI_2035><TOI_2035>85.413169124033</TOI_2035><FR_2036>61.636276765974</FR_2036><OI_2036>30.043095038204</OI_2036><TOI_2036>91.679371804178</TOI_2036><FR_2037>66.567178907252</FR_2037><OI_2037>31.845680740497</OI_2037><TOI_2037>98.412859647749</TOI_2037><FR_2038>71.892553219832</FR_2038><OI_2038>33.756421584926</OI_2038><TOI_2038>105.64897480476</TOI_2038><FR_2039>77.643957477419</FR_2039><OI_2039>35.781806880022</OI_2039><TOI_2039>113.42576435744</TOI_2039><FR_2040>83.855474075612</FR_2040><OI_2040>37.928715292823</OI_2040><TOI_2040>121.78418936844</TOI_2040><FR_2041>90.563912001661</FR_2041><OI_2041>40.204438210393</OI_2041><TOI_2041>130.76835021205</TOI_2041><FR_2042>97.809024961794</FR_2042><OI_2042>42.616704503016</OI_2042><TOI_2042>140.42572946481</TOI_2042><FR_2043>105.63374695874</FR_2043><OI_2043>45.173706773197</OI_2043><TOI_2043>150.80745373193</TOI_2043><FR_2044>114.08444671544</FR_2044><OI_2044>47.884129179589</OI_2044><TOI_2044>161.96857589503</TOI_2044><FR_2045>123.21120245267</FR_2045><OI_2045>50.757176930365</OI_2045><TOI_2045>173.96837938304</TOI_2045><sid>1</sid></row><row><id>9</id><FR_2012>9.72</FR_2012><OI_2012>7.42</OI_2012><TOI_2012>17.14</TOI_2012><FR_2013>10.4976</FR_2013><OI_2013>7.8652</OI_2013><TOI_2013>18.3628</TOI_2013><FR_2014>11.337408</FR_2014><OI_2014>8.337112</OI_2014><TOI_2014>19.67452</TOI_2014><FR_2015>12.24440064</FR_2015><OI_2015>8.83733872</OI_2015><TOI_2015>21.08173936</TOI_2015><FR_2016>13.2239526912</FR_2016><OI_2016>9.3675790432</OI_2016><TOI_2016>22.5915317344</TOI_2016><FR_2017>14.281868906496</FR_2017><OI_2017>9.929633785792</OI_2017><TOI_2017>24.211502692288</TOI_2017><FR_2018>15.424418419016</FR_2018><OI_2018>10.52541181294</OI_2018><TOI_2018>25.949830231955</TOI_2018><FR_2019>16.658371892537</FR_2019><OI_2019>11.156936521716</OI_2019><TOI_2019>27.815308414253</TOI_2019><FR_2020>17.99104164394</FR_2020><OI_2020>11.826352713019</OI_2020><TOI_2020>29.817394356959</TOI_2020><FR_2021>19.430324975455</FR_2021><OI_2021>12.5359338758</OI_2021><TOI_2021>31.966258851255</TOI_2021><FR_2022>20.984750973492</FR_2022><OI_2022>13.288089908348</OI_2022><TOI_2022>34.272840881839</TOI_2022><FR_2023>22.663531051371</FR_2023><OI_2023>14.085375302849</OI_2023><TOI_2023>36.74890635422</TOI_2023><FR_2024>24.47661353548</FR_2024><OI_2024>14.93049782102</OI_2024><TOI_2024>39.4071113565</TOI_2024><FR_2025>26.434742618319</FR_2025><OI_2025>15.826327690281</OI_2025><TOI_2025>42.2610703086</TOI_2025><FR_2026>28.549522027784</FR_2026><OI_2026>16.775907351698</OI_2026><TOI_2026>45.325429379482</TOI_2026><FR_2027>30.833483790007</FR_2027><OI_2027>17.7824617928</OI_2027><TOI_2027>48.615945582807</TOI_2027><FR_2028>33.300162493208</FR_2028><OI_2028>18.849409500368</OI_2028><TOI_2028>52.149571993575</TOI_2028><FR_2029>35.964175492664</FR_2029><OI_2029>19.98037407039</OI_2029><TOI_2029>55.944549563054</TOI_2029><FR_2030>38.841309532078</FR_2030><OI_2030>21.179196514613</OI_2030><TOI_2030>60.020506046691</TOI_2030><FR_2031>41.948614294644</FR_2031><OI_2031>22.44994830549</OI_2031><TOI_2031>64.398562600134</TOI_2031><FR_2032>45.304503438215</FR_2032><OI_2032>23.796945203819</OI_2032><TOI_2032>69.101448642035</TOI_2032><FR_2033>48.928863713272</FR_2033><OI_2033>25.224761916048</OI_2033><TOI_2033>74.153625629321</TOI_2033><FR_2034>52.843172810334</FR_2034><OI_2034>26.738247631011</OI_2034><TOI_2034>79.581420441346</TOI_2034><FR_2035>57.070626635161</FR_2035><OI_2035>28.342542488872</OI_2035><TOI_2035>85.413169124033</TOI_2035><FR_2036>61.636276765974</FR_2036><OI_2036>30.043095038204</OI_2036><TOI_2036>91.679371804178</TOI_2036><FR_2037>66.567178907252</FR_2037><OI_2037>31.845680740497</OI_2037><TOI_2037>98.412859647749</TOI_2037><FR_2038>71.892553219832</FR_2038><OI_2038>33.756421584926</OI_2038><TOI_2038>105.64897480476</TOI_2038><FR_2039>77.643957477419</FR_2039><OI_2039>35.781806880022</OI_2039><TOI_2039>113.42576435744</TOI_2039><FR_2040>83.855474075612</FR_2040><OI_2040>37.928715292823</OI_2040><TOI_2040>121.78418936844</TOI_2040><FR_2041>90.563912001661</FR_2041><OI_2041>40.204438210393</OI_2041><TOI_2041>130.76835021205</TOI_2041><FR_2042>97.809024961794</FR_2042><OI_2042>42.616704503016</OI_2042><TOI_2042>140.42572946481</TOI_2042><FR_2043>105.63374695874</FR_2043><OI_2043>45.173706773197</OI_2043><TOI_2043>150.80745373193</TOI_2043><FR_2044>114.08444671544</FR_2044><OI_2044>47.884129179589</OI_2044><TOI_2044>161.96857589503</TOI_2044><FR_2045>123.21120245267</FR_2045><OI_2045>50.757176930365</OI_2045><TOI_2045>173.96837938304</TOI_2045><sid>1</sid></row><row><id>10</id><FR_2012>9.72</FR_2012><OI_2012>7.42</OI_2012><TOI_2012>17.14</TOI_2012><FR_2013>10.4976</FR_2013><OI_2013>7.8652</OI_2013><TOI_2013>18.3628</TOI_2013><FR_2014>11.337408</FR_2014><OI_2014>8.337112</OI_2014><TOI_2014>19.67452</TOI_2014><FR_2015>12.24440064</FR_2015><OI_2015>8.83733872</OI_2015><TOI_2015>21.08173936</TOI_2015><FR_2016>13.2239526912</FR_2016><OI_2016>9.3675790432</OI_2016><TOI_2016>22.5915317344</TOI_2016><FR_2017>14.281868906496</FR_2017><OI_2017>9.929633785792</OI_2017><TOI_2017>24.211502692288</TOI_2017><FR_2018>15.424418419016</FR_2018><OI_2018>10.52541181294</OI_2018><TOI_2018>25.949830231955</TOI_2018><FR_2019>16.658371892537</FR_2019><OI_2019>11.156936521716</OI_2019><TOI_2019>27.815308414253</TOI_2019><FR_2020>17.99104164394</FR_2020><OI_2020>11.826352713019</OI_2020><TOI_2020>29.817394356959</TOI_2020><FR_2021>19.430324975455</FR_2021><OI_2021>12.5359338758</OI_2021><TOI_2021>31.966258851255</TOI_2021><FR_2022>20.984750973492</FR_2022><OI_2022>13.288089908348</OI_2022><TOI_2022>34.272840881839</TOI_2022><FR_2023>22.663531051371</FR_2023><OI_2023>14.085375302849</OI_2023><TOI_2023>36.74890635422</TOI_2023><FR_2024>24.47661353548</FR_2024><OI_2024>14.93049782102</OI_2024><TOI_2024>39.4071113565</TOI_2024><FR_2025>26.434742618319</FR_2025><OI_2025>15.826327690281</OI_2025><TOI_2025>42.2610703086</TOI_2025><FR_2026>28.549522027784</FR_2026><OI_2026>16.775907351698</OI_2026><TOI_2026>45.325429379482</TOI_2026><FR_2027>30.833483790007</FR_2027><OI_2027>17.7824617928</OI_2027><TOI_2027>48.615945582807</TOI_2027><FR_2028>33.300162493208</FR_2028><OI_2028>18.849409500368</OI_2028><TOI_2028>52.149571993575</TOI_2028><FR_2029>35.964175492664</FR_2029><OI_2029>19.98037407039</OI_2029><TOI_2029>55.944549563054</TOI_2029><FR_2030>38.841309532078</FR_2030><OI_2030>21.179196514613</OI_2030><TOI_2030>60.020506046691</TOI_2030><FR_2031>41.948614294644</FR_2031><OI_2031>22.44994830549</OI_2031><TOI_2031>64.398562600134</TOI_2031><FR_2032>45.304503438215</FR_2032><OI_2032>23.796945203819</OI_2032><TOI_2032>69.101448642035</TOI_2032><FR_2033>48.928863713272</FR_2033><OI_2033>25.224761916048</OI_2033><TOI_2033>74.153625629321</TOI_2033><FR_2034>52.843172810334</FR_2034><OI_2034>26.738247631011</OI_2034><TOI_2034>79.581420441346</TOI_2034><FR_2035>57.070626635161</FR_2035><OI_2035>28.342542488872</OI_2035><TOI_2035>85.413169124033</TOI_2035><FR_2036>61.636276765974</FR_2036><OI_2036>30.043095038204</OI_2036><TOI_2036>91.679371804178</TOI_2036><FR_2037>66.567178907252</FR_2037><OI_2037>31.845680740497</OI_2037><TOI_2037>98.412859647749</TOI_2037><FR_2038>71.892553219832</FR_2038><OI_2038>33.756421584926</OI_2038><TOI_2038>105.64897480476</TOI_2038><FR_2039>77.643957477419</FR_2039><OI_2039>35.781806880022</OI_2039><TOI_2039>113.42576435744</TOI_2039><FR_2040>83.855474075612</FR_2040><OI_2040>37.928715292823</OI_2040><TOI_2040>121.78418936844</TOI_2040><FR_2041>90.563912001661</FR_2041><OI_2041>40.204438210393</OI_2041><TOI_2041>130.76835021205</TOI_2041><FR_2042>97.809024961794</FR_2042><OI_2042>42.616704503016</OI_2042><TOI_2042>140.42572946481</TOI_2042><FR_2043>105.63374695874</FR_2043><OI_2043>45.173706773197</OI_2043><TOI_2043>150.80745373193</TOI_2043><FR_2044>114.08444671544</FR_2044><OI_2044>47.884129179589</OI_2044><TOI_2044>161.96857589503</TOI_2044><FR_2045>123.21120245267</FR_2045><OI_2045>50.757176930365</OI_2045><TOI_2045>173.96837938304</TOI_2045><sid>1</sid></row><row><id>11</id><FR_2012>9.72</FR_2012><OI_2012>7.42</OI_2012><TOI_2012>17.14</TOI_2012><FR_2013>10.4976</FR_2013><OI_2013>7.8652</OI_2013><TOI_2013>18.3628</TOI_2013><FR_2014>11.337408</FR_2014><OI_2014>8.337112</OI_2014><TOI_2014>19.67452</TOI_2014><FR_2015>12.24440064</FR_2015><OI_2015>8.83733872</OI_2015><TOI_2015>21.08173936</TOI_2015><FR_2016>13.2239526912</FR_2016><OI_2016>9.3675790432</OI_2016><TOI_2016>22.5915317344</TOI_2016><FR_2017>14.281868906496</FR_2017><OI_2017>9.929633785792</OI_2017><TOI_2017>24.211502692288</TOI_2017><FR_2018>15.424418419016</FR_2018><OI_2018>10.52541181294</OI_2018><TOI_2018>25.949830231955</TOI_2018><FR_2019>16.658371892537</FR_2019><OI_2019>11.156936521716</OI_2019><TOI_2019>27.815308414253</TOI_2019><FR_2020>17.99104164394</FR_2020><OI_2020>11.826352713019</OI_2020><TOI_2020>29.817394356959</TOI_2020><FR_2021>19.430324975455</FR_2021><OI_2021>12.5359338758</OI_2021><TOI_2021>31.966258851255</TOI_2021><FR_2022>20.984750973492</FR_2022><OI_2022>13.288089908348</OI_2022><TOI_2022>34.272840881839</TOI_2022><FR_2023>22.663531051371</FR_2023><OI_2023>14.085375302849</OI_2023><TOI_2023>36.74890635422</TOI_2023><FR_2024>24.47661353548</FR_2024><OI_2024>14.93049782102</OI_2024><TOI_2024>39.4071113565</TOI_2024><FR_2025>26.434742618319</FR_2025><OI_2025>15.826327690281</OI_2025><TOI_2025>42.2610703086</TOI_2025><FR_2026>28.549522027784</FR_2026><OI_2026>16.775907351698</OI_2026><TOI_2026>45.325429379482</TOI_2026><FR_2027>30.833483790007</FR_2027><OI_2027>17.7824617928</OI_2027><TOI_2027>48.615945582807</TOI_2027><FR_2028>33.300162493208</FR_2028><OI_2028>18.849409500368</OI_2028><TOI_2028>52.149571993575</TOI_2028><FR_2029>35.964175492664</FR_2029><OI_2029>19.98037407039</OI_2029><TOI_2029>55.944549563054</TOI_2029><FR_2030>38.841309532078</FR_2030><OI_2030>21.179196514613</OI_2030><TOI_2030>60.020506046691</TOI_2030><FR_2031>41.948614294644</FR_2031><OI_2031>22.44994830549</OI_2031><TOI_2031>64.398562600134</TOI_2031><FR_2032>45.304503438215</FR_2032><OI_2032>23.796945203819</OI_2032><TOI_2032>69.101448642035</TOI_2032><FR_2033>48.928863713272</FR_2033><OI_2033>25.224761916048</OI_2033><TOI_2033>74.153625629321</TOI_2033><FR_2034>52.843172810334</FR_2034><OI_2034>26.738247631011</OI_2034><TOI_2034>79.581420441346</TOI_2034><FR_2035>57.070626635161</FR_2035><OI_2035>28.342542488872</OI_2035><TOI_2035>85.413169124033</TOI_2035><FR_2036>61.636276765974</FR_2036><OI_2036>30.043095038204</OI_2036><TOI_2036>91.679371804178</TOI_2036><FR_2037>66.567178907252</FR_2037><OI_2037>31.845680740497</OI_2037><TOI_2037>98.412859647749</TOI_2037><FR_2038>71.892553219832</FR_2038><OI_2038>33.756421584926</OI_2038><TOI_2038>105.64897480476</TOI_2038><FR_2039>77.643957477419</FR_2039><OI_2039>35.781806880022</OI_2039><TOI_2039>113.42576435744</TOI_2039><FR_2040>83.855474075612</FR_2040><OI_2040>37.928715292823</OI_2040><TOI_2040>121.78418936844</TOI_2040><FR_2041>90.563912001661</FR_2041><OI_2041>40.204438210393</OI_2041><TOI_2041>130.76835021205</TOI_2041><FR_2042>97.809024961794</FR_2042><OI_2042>42.616704503016</OI_2042><TOI_2042>140.42572946481</TOI_2042><FR_2043>105.63374695874</FR_2043><OI_2043>45.173706773197</OI_2043><TOI_2043>150.80745373193</TOI_2043><FR_2044>114.08444671544</FR_2044><OI_2044>47.884129179589</OI_2044><TOI_2044>161.96857589503</TOI_2044><FR_2045>123.21120245267</FR_2045><OI_2045>50.757176930365</OI_2045><TOI_2045>173.96837938304</TOI_2045><sid>1</sid></row><row><id>12</id><FR_2012>9.72</FR_2012><OI_2012>7.42</OI_2012><TOI_2012>17.14</TOI_2012><FR_2013>10.4976</FR_2013><OI_2013>7.8652</OI_2013><TOI_2013>18.3628</TOI_2013><FR_2014>11.337408</FR_2014><OI_2014>8.337112</OI_2014><TOI_2014>19.67452</TOI_2014><FR_2015>12.24440064</FR_2015><OI_2015>8.83733872</OI_2015><TOI_2015>21.08173936</TOI_2015><FR_2016>13.2239526912</FR_2016><OI_2016>9.3675790432</OI_2016><TOI_2016>22.5915317344</TOI_2016><FR_2017>14.281868906496</FR_2017><OI_2017>9.929633785792</OI_2017><TOI_2017>24.211502692288</TOI_2017><FR_2018>15.424418419016</FR_2018><OI_2018>10.52541181294</OI_2018><TOI_2018>25.949830231955</TOI_2018><FR_2019>16.658371892537</FR_2019><OI_2019>11.156936521716</OI_2019><TOI_2019>27.815308414253</TOI_2019><FR_2020>17.99104164394</FR_2020><OI_2020>11.826352713019</OI_2020><TOI_2020>29.817394356959</TOI_2020><FR_2021>19.430324975455</FR_2021><OI_2021>12.5359338758</OI_2021><TOI_2021>31.966258851255</TOI_2021><FR_2022>20.984750973492</FR_2022><OI_2022>13.288089908348</OI_2022><TOI_2022>34.272840881839</TOI_2022><FR_2023>22.663531051371</FR_2023><OI_2023>14.085375302849</OI_2023><TOI_2023>36.74890635422</TOI_2023><FR_2024>24.47661353548</FR_2024><OI_2024>14.93049782102</OI_2024><TOI_2024>39.4071113565</TOI_2024><FR_2025>26.434742618319</FR_2025><OI_2025>15.826327690281</OI_2025><TOI_2025>42.2610703086</TOI_2025><FR_2026>28.549522027784</FR_2026><OI_2026>16.775907351698</OI_2026><TOI_2026>45.325429379482</TOI_2026><FR_2027>30.833483790007</FR_2027><OI_2027>17.7824617928</OI_2027><TOI_2027>48.615945582807</TOI_2027><FR_2028>33.300162493208</FR_2028><OI_2028>18.849409500368</OI_2028><TOI_2028>52.149571993575</TOI_2028><FR_2029>35.964175492664</FR_2029><OI_2029>19.98037407039</OI_2029><TOI_2029>55.944549563054</TOI_2029><FR_2030>38.841309532078</FR_2030><OI_2030>21.179196514613</OI_2030><TOI_2030>60.020506046691</TOI_2030><FR_2031>41.948614294644</FR_2031><OI_2031>22.44994830549</OI_2031><TOI_2031>64.398562600134</TOI_2031><FR_2032>45.304503438215</FR_2032><OI_2032>23.796945203819</OI_2032><TOI_2032>69.101448642035</TOI_2032><FR_2033>48.928863713272</FR_2033><OI_2033>25.224761916048</OI_2033><TOI_2033>74.153625629321</TOI_2033><FR_2034>52.843172810334</FR_2034><OI_2034>26.738247631011</OI_2034><TOI_2034>79.581420441346</TOI_2034><FR_2035>57.070626635161</FR_2035><OI_2035>28.342542488872</OI_2035><TOI_2035>85.413169124033</TOI_2035><FR_2036>61.636276765974</FR_2036><OI_2036>30.043095038204</OI_2036><TOI_2036>91.679371804178</TOI_2036><FR_2037>66.567178907252</FR_2037><OI_2037>31.845680740497</OI_2037><TOI_2037>98.412859647749</TOI_2037><FR_2038>71.892553219832</FR_2038><OI_2038>33.756421584926</OI_2038><TOI_2038>105.64897480476</TOI_2038><FR_2039>77.643957477419</FR_2039><OI_2039>35.781806880022</OI_2039><TOI_2039>113.42576435744</TOI_2039><FR_2040>83.855474075612</FR_2040><OI_2040>37.928715292823</OI_2040><TOI_2040>121.78418936844</TOI_2040><FR_2041>90.563912001661</FR_2041><OI_2041>40.204438210393</OI_2041><TOI_2041>130.76835021205</TOI_2041><FR_2042>97.809024961794</FR_2042><OI_2042>42.616704503016</OI_2042><TOI_2042>140.42572946481</TOI_2042><FR_2043>105.63374695874</FR_2043><OI_2043>45.173706773197</OI_2043><TOI_2043>150.80745373193</TOI_2043><FR_2044>114.08444671544</FR_2044><OI_2044>47.884129179589</OI_2044><TOI_2044>161.96857589503</TOI_2044><FR_2045>123.21120245267</FR_2045><OI_2045>50.757176930365</OI_2045><TOI_2045>173.96837938304</TOI_2045><sid>1</sid></row><row><id>13</id><FR_2012>9.72</FR_2012><OI_2012>7.42</OI_2012><TOI_2012>17.14</TOI_2012><FR_2013>10.4976</FR_2013><OI_2013>7.8652</OI_2013><TOI_2013>18.3628</TOI_2013><FR_2014>11.337408</FR_2014><OI_2014>8.337112</OI_2014><TOI_2014>19.67452</TOI_2014><FR_2015>12.24440064</FR_2015><OI_2015>8.83733872</OI_2015><TOI_2015>21.08173936</TOI_2015><FR_2016>13.2239526912</FR_2016><OI_2016>9.3675790432</OI_2016><TOI_2016>22.5915317344</TOI_2016><FR_2017>14.281868906496</FR_2017><OI_2017>9.929633785792</OI_2017><TOI_2017>24.211502692288</TOI_2017><FR_2018>15.424418419016</FR_2018><OI_2018>10.52541181294</OI_2018><TOI_2018>25.949830231955</TOI_2018><FR_2019>16.658371892537</FR_2019><OI_2019>11.156936521716</OI_2019><TOI_2019>27.815308414253</TOI_2019><FR_2020>17.99104164394</FR_2020><OI_2020>11.826352713019</OI_2020><TOI_2020>29.817394356959</TOI_2020><FR_2021>19.430324975455</FR_2021><OI_2021>12.5359338758</OI_2021><TOI_2021>31.966258851255</TOI_2021><FR_2022>20.984750973492</FR_2022><OI_2022>13.288089908348</OI_2022><TOI_2022>34.272840881839</TOI_2022><FR_2023>22.663531051371</FR_2023><OI_2023>14.085375302849</OI_2023><TOI_2023>36.74890635422</TOI_2023><FR_2024>24.47661353548</FR_2024><OI_2024>14.93049782102</OI_2024><TOI_2024>39.4071113565</TOI_2024><FR_2025>26.434742618319</FR_2025><OI_2025>15.826327690281</OI_2025><TOI_2025>42.2610703086</TOI_2025><FR_2026>28.549522027784</FR_2026><OI_2026>16.775907351698</OI_2026><TOI_2026>45.325429379482</TOI_2026><FR_2027>30.833483790007</FR_2027><OI_2027>17.7824617928</OI_2027><TOI_2027>48.615945582807</TOI_2027><FR_2028>33.300162493208</FR_2028><OI_2028>18.849409500368</OI_2028><TOI_2028>52.149571993575</TOI_2028><FR_2029>35.964175492664</FR_2029><OI_2029>19.98037407039</OI_2029><TOI_2029>55.944549563054</TOI_2029><FR_2030>38.841309532078</FR_2030><OI_2030>21.179196514613</OI_2030><TOI_2030>60.020506046691</TOI_2030><FR_2031>41.948614294644</FR_2031><OI_2031>22.44994830549</OI_2031><TOI_2031>64.398562600134</TOI_2031><FR_2032>45.304503438215</FR_2032><OI_2032>23.796945203819</OI_2032><TOI_2032>69.101448642035</TOI_2032><FR_2033>48.928863713272</FR_2033><OI_2033>25.224761916048</OI_2033><TOI_2033>74.153625629321</TOI_2033><FR_2034>52.843172810334</FR_2034><OI_2034>26.738247631011</OI_2034><TOI_2034>79.581420441346</TOI_2034><FR_2035>57.070626635161</FR_2035><OI_2035>28.342542488872</OI_2035><TOI_2035>85.413169124033</TOI_2035><FR_2036>61.636276765974</FR_2036><OI_2036>30.043095038204</OI_2036><TOI_2036>91.679371804178</TOI_2036><FR_2037>66.567178907252</FR_2037><OI_2037>31.845680740497</OI_2037><TOI_2037>98.412859647749</TOI_2037><FR_2038>71.892553219832</FR_2038><OI_2038>33.756421584926</OI_2038><TOI_2038>105.64897480476</TOI_2038><FR_2039>77.643957477419</FR_2039><OI_2039>35.781806880022</OI_2039><TOI_2039>113.42576435744</TOI_2039><FR_2040>83.855474075612</FR_2040><OI_2040>37.928715292823</OI_2040><TOI_2040>121.78418936844</TOI_2040><FR_2041>90.563912001661</FR_2041><OI_2041>40.204438210393</OI_2041><TOI_2041>130.76835021205</TOI_2041><FR_2042>97.809024961794</FR_2042><OI_2042>42.616704503016</OI_2042><TOI_2042>140.42572946481</TOI_2042><FR_2043>105.63374695874</FR_2043><OI_2043>45.173706773197</OI_2043><TOI_2043>150.80745373193</TOI_2043><FR_2044>114.08444671544</FR_2044><OI_2044>47.884129179589</OI_2044><TOI_2044>161.96857589503</TOI_2044><FR_2045>123.21120245267</FR_2045><OI_2045>50.757176930365</OI_2045><TOI_2045>173.96837938304</TOI_2045><sid>1</sid></row></data></cal_revenues>
