<?xml version="1.0" encoding="utf-8"?>
<cal_totalpurchase><meta><autoIncrement>12</autoIncrement></meta><data><row><id>1</id><E_2012>0</E_2012><LC_2012>0</LC_2012><EP_MYR_2012>0</EP_MYR_2012><E_2013>0</E_2013><LC_2013>0</LC_2013><EP_MYR_2013>0</EP_MYR_2013><E_2014>0</E_2014><LC_2014>0</LC_2014><EP_MYR_2014>0</EP_MYR_2014><E_2015>0</E_2015><LC_2015>0</LC_2015><EP_MYR_2015>0</EP_MYR_2015><E_2016>0</E_2016><LC_2016>0</LC_2016><EP_MYR_2016>0</EP_MYR_2016><E_2017>0</E_2017><LC_2017>0</LC_2017><EP_MYR_2017>0</EP_MYR_2017><E_2018>0</E_2018><LC_2018>0</LC_2018><EP_MYR_2018>0</EP_MYR_2018><E_2019>0</E_2019><LC_2019>0</LC_2019><EP_MYR_2019>0</EP_MYR_2019><E_2020>0</E_2020><LC_2020>0</LC_2020><EP_MYR_2020>0</EP_MYR_2020><E_2021>0</E_2021><LC_2021>0</LC_2021><EP_MYR_2021>0</EP_MYR_2021><E_2022>0</E_2022><LC_2022>0</LC_2022><EP_MYR_2022>0</EP_MYR_2022><E_2023>0</E_2023><LC_2023>0</LC_2023><EP_MYR_2023>0</EP_MYR_2023><E_2024>0</E_2024><LC_2024>0</LC_2024><EP_MYR_2024>0</EP_MYR_2024><E_2025>0</E_2025><LC_2025>0</LC_2025><EP_MYR_2025>0</EP_MYR_2025><E_2026>0</E_2026><LC_2026>0</LC_2026><EP_MYR_2026>0</EP_MYR_2026><E_2027>0</E_2027><LC_2027>0</LC_2027><EP_MYR_2027>0</EP_MYR_2027><E_2028>0</E_2028><LC_2028>0</LC_2028><EP_MYR_2028>0</EP_MYR_2028><E_2029>0</E_2029><LC_2029>0</LC_2029><EP_MYR_2029>0</EP_MYR_2029><E_2030>0</E_2030><LC_2030>0</LC_2030><EP_MYR_2030>0</EP_MYR_2030><E_2031>0</E_2031><LC_2031>0</LC_2031><EP_MYR_2031>0</EP_MYR_2031><E_2032>0</E_2032><LC_2032>0</LC_2032><EP_MYR_2032>0</EP_MYR_2032><E_2033>0</E_2033><LC_2033>0</LC_2033><EP_MYR_2033>0</EP_MYR_2033><E_2034>0</E_2034><LC_2034>0</LC_2034><EP_MYR_2034>0</EP_MYR_2034><E_2035>0</E_2035><LC_2035>0</LC_2035><EP_MYR_2035>0</EP_MYR_2035><E_2036>0</E_2036><LC_2036>0</LC_2036><EP_MYR_2036>0</EP_MYR_2036><E_2037>0</E_2037><LC_2037>0</LC_2037><EP_MYR_2037>0</EP_MYR_2037><E_2038>0</E_2038><LC_2038>0</LC_2038><EP_MYR_2038>0</EP_MYR_2038><E_2039>0</E_2039><LC_2039>0</LC_2039><EP_MYR_2039>0</EP_MYR_2039><E_2040>0</E_2040><LC_2040>0</LC_2040><EP_MYR_2040>0</EP_MYR_2040><E_2041>0</E_2041><LC_2041>0</LC_2041><EP_MYR_2041>0</EP_MYR_2041><E_2042>0</E_2042><LC_2042>0</LC_2042><EP_MYR_2042>0</EP_MYR_2042><E_2043>0</E_2043><LC_2043>0</LC_2043><EP_MYR_2043>0</EP_MYR_2043><E_2044>0</E_2044><LC_2044>0</LC_2044><EP_MYR_2044>0</EP_MYR_2044><E_2045>0</E_2045><LC_2045>0</LC_2045><EP_MYR_2045>0</EP_MYR_2045><sid>1</sid></row><row><id>2</id><E_2012>0</E_2012><LC_2012>0</LC_2012><EP_MYR_2012>0</EP_MYR_2012><E_2013>0</E_2013><LC_2013>0</LC_2013><EP_MYR_2013>0</EP_MYR_2013><E_2014>0</E_2014><LC_2014>0</LC_2014><EP_MYR_2014>0</EP_MYR_2014><E_2015>0</E_2015><LC_2015>0</LC_2015><EP_MYR_2015>0</EP_MYR_2015><E_2016>0</E_2016><LC_2016>0</LC_2016><EP_MYR_2016>0</EP_MYR_2016><E_2017>0</E_2017><LC_2017>0</LC_2017><EP_MYR_2017>0</EP_MYR_2017><E_2018>0</E_2018><LC_2018>0</LC_2018><EP_MYR_2018>0</EP_MYR_2018><E_2019>0</E_2019><LC_2019>0</LC_2019><EP_MYR_2019>0</EP_MYR_2019><E_2020>0</E_2020><LC_2020>0</LC_2020><EP_MYR_2020>0</EP_MYR_2020><E_2021>0</E_2021><LC_2021>0</LC_2021><EP_MYR_2021>0</EP_MYR_2021><E_2022>0</E_2022><LC_2022>0</LC_2022><EP_MYR_2022>0</EP_MYR_2022><E_2023>0</E_2023><LC_2023>0</LC_2023><EP_MYR_2023>0</EP_MYR_2023><E_2024>0</E_2024><LC_2024>0</LC_2024><EP_MYR_2024>0</EP_MYR_2024><E_2025>0</E_2025><LC_2025>0</LC_2025><EP_MYR_2025>0</EP_MYR_2025><E_2026>0</E_2026><LC_2026>0</LC_2026><EP_MYR_2026>0</EP_MYR_2026><E_2027>0</E_2027><LC_2027>0</LC_2027><EP_MYR_2027>0</EP_MYR_2027><E_2028>0</E_2028><LC_2028>0</LC_2028><EP_MYR_2028>0</EP_MYR_2028><E_2029>0</E_2029><LC_2029>0</LC_2029><EP_MYR_2029>0</EP_MYR_2029><E_2030>0</E_2030><LC_2030>0</LC_2030><EP_MYR_2030>0</EP_MYR_2030><E_2031>0</E_2031><LC_2031>0</LC_2031><EP_MYR_2031>0</EP_MYR_2031><E_2032>0</E_2032><LC_2032>0</LC_2032><EP_MYR_2032>0</EP_MYR_2032><E_2033>0</E_2033><LC_2033>0</LC_2033><EP_MYR_2033>0</EP_MYR_2033><E_2034>0</E_2034><LC_2034>0</LC_2034><EP_MYR_2034>0</EP_MYR_2034><E_2035>0</E_2035><LC_2035>0</LC_2035><EP_MYR_2035>0</EP_MYR_2035><E_2036>0</E_2036><LC_2036>0</LC_2036><EP_MYR_2036>0</EP_MYR_2036><E_2037>0</E_2037><LC_2037>0</LC_2037><EP_MYR_2037>0</EP_MYR_2037><E_2038>0</E_2038><LC_2038>0</LC_2038><EP_MYR_2038>0</EP_MYR_2038><E_2039>0</E_2039><LC_2039>0</LC_2039><EP_MYR_2039>0</EP_MYR_2039><E_2040>0</E_2040><LC_2040>0</LC_2040><EP_MYR_2040>0</EP_MYR_2040><E_2041>0</E_2041><LC_2041>0</LC_2041><EP_MYR_2041>0</EP_MYR_2041><E_2042>0</E_2042><LC_2042>0</LC_2042><EP_MYR_2042>0</EP_MYR_2042><E_2043>0</E_2043><LC_2043>0</LC_2043><EP_MYR_2043>0</EP_MYR_2043><E_2044>0</E_2044><LC_2044>0</LC_2044><EP_MYR_2044>0</EP_MYR_2044><E_2045>0</E_2045><LC_2045>0</LC_2045><EP_MYR_2045>0</EP_MYR_2045><sid>1</sid></row><row><id>3</id><E_2012>0</E_2012><LC_2012>0</LC_2012><EP_MYR_2012>0</EP_MYR_2012><E_2013>0</E_2013><LC_2013>0</LC_2013><EP_MYR_2013>0</EP_MYR_2013><E_2014>0</E_2014><LC_2014>0</LC_2014><EP_MYR_2014>0</EP_MYR_2014><E_2015>0</E_2015><LC_2015>0</LC_2015><EP_MYR_2015>0</EP_MYR_2015><E_2016>0</E_2016><LC_2016>0</LC_2016><EP_MYR_2016>0</EP_MYR_2016><E_2017>0</E_2017><LC_2017>0</LC_2017><EP_MYR_2017>0</EP_MYR_2017><E_2018>0</E_2018><LC_2018>0</LC_2018><EP_MYR_2018>0</EP_MYR_2018><E_2019>0</E_2019><LC_2019>0</LC_2019><EP_MYR_2019>0</EP_MYR_2019><E_2020>0</E_2020><LC_2020>0</LC_2020><EP_MYR_2020>0</EP_MYR_2020><E_2021>0</E_2021><LC_2021>0</LC_2021><EP_MYR_2021>0</EP_MYR_2021><E_2022>0</E_2022><LC_2022>0</LC_2022><EP_MYR_2022>0</EP_MYR_2022><E_2023>0</E_2023><LC_2023>0</LC_2023><EP_MYR_2023>0</EP_MYR_2023><E_2024>0</E_2024><LC_2024>0</LC_2024><EP_MYR_2024>0</EP_MYR_2024><E_2025>0</E_2025><LC_2025>0</LC_2025><EP_MYR_2025>0</EP_MYR_2025><E_2026>0</E_2026><LC_2026>0</LC_2026><EP_MYR_2026>0</EP_MYR_2026><E_2027>0</E_2027><LC_2027>0</LC_2027><EP_MYR_2027>0</EP_MYR_2027><E_2028>0</E_2028><LC_2028>0</LC_2028><EP_MYR_2028>0</EP_MYR_2028><E_2029>0</E_2029><LC_2029>0</LC_2029><EP_MYR_2029>0</EP_MYR_2029><E_2030>0</E_2030><LC_2030>0</LC_2030><EP_MYR_2030>0</EP_MYR_2030><E_2031>0</E_2031><LC_2031>0</LC_2031><EP_MYR_2031>0</EP_MYR_2031><E_2032>0</E_2032><LC_2032>0</LC_2032><EP_MYR_2032>0</EP_MYR_2032><E_2033>0</E_2033><LC_2033>0</LC_2033><EP_MYR_2033>0</EP_MYR_2033><E_2034>0</E_2034><LC_2034>0</LC_2034><EP_MYR_2034>0</EP_MYR_2034><E_2035>0</E_2035><LC_2035>0</LC_2035><EP_MYR_2035>0</EP_MYR_2035><E_2036>0</E_2036><LC_2036>0</LC_2036><EP_MYR_2036>0</EP_MYR_2036><E_2037>0</E_2037><LC_2037>0</LC_2037><EP_MYR_2037>0</EP_MYR_2037><E_2038>0</E_2038><LC_2038>0</LC_2038><EP_MYR_2038>0</EP_MYR_2038><E_2039>0</E_2039><LC_2039>0</LC_2039><EP_MYR_2039>0</EP_MYR_2039><E_2040>0</E_2040><LC_2040>0</LC_2040><EP_MYR_2040>0</EP_MYR_2040><E_2041>0</E_2041><LC_2041>0</LC_2041><EP_MYR_2041>0</EP_MYR_2041><E_2042>0</E_2042><LC_2042>0</LC_2042><EP_MYR_2042>0</EP_MYR_2042><E_2043>0</E_2043><LC_2043>0</LC_2043><EP_MYR_2043>0</EP_MYR_2043><E_2044>0</E_2044><LC_2044>0</LC_2044><EP_MYR_2044>0</EP_MYR_2044><E_2045>0</E_2045><LC_2045>0</LC_2045><EP_MYR_2045>0</EP_MYR_2045><sid>1</sid></row><row><id>4</id><E_2012>0</E_2012><LC_2012>0</LC_2012><EP_MYR_2012>0</EP_MYR_2012><E_2013>0</E_2013><LC_2013>0</LC_2013><EP_MYR_2013>0</EP_MYR_2013><E_2014>0</E_2014><LC_2014>0</LC_2014><EP_MYR_2014>0</EP_MYR_2014><E_2015>0</E_2015><LC_2015>0</LC_2015><EP_MYR_2015>0</EP_MYR_2015><E_2016>0</E_2016><LC_2016>0</LC_2016><EP_MYR_2016>0</EP_MYR_2016><E_2017>0</E_2017><LC_2017>0</LC_2017><EP_MYR_2017>0</EP_MYR_2017><E_2018>0</E_2018><LC_2018>0</LC_2018><EP_MYR_2018>0</EP_MYR_2018><E_2019>0</E_2019><LC_2019>0</LC_2019><EP_MYR_2019>0</EP_MYR_2019><E_2020>0</E_2020><LC_2020>0</LC_2020><EP_MYR_2020>0</EP_MYR_2020><E_2021>0</E_2021><LC_2021>0</LC_2021><EP_MYR_2021>0</EP_MYR_2021><E_2022>0</E_2022><LC_2022>0</LC_2022><EP_MYR_2022>0</EP_MYR_2022><E_2023>0</E_2023><LC_2023>0</LC_2023><EP_MYR_2023>0</EP_MYR_2023><E_2024>0</E_2024><LC_2024>0</LC_2024><EP_MYR_2024>0</EP_MYR_2024><E_2025>0</E_2025><LC_2025>0</LC_2025><EP_MYR_2025>0</EP_MYR_2025><E_2026>0</E_2026><LC_2026>0</LC_2026><EP_MYR_2026>0</EP_MYR_2026><E_2027>0</E_2027><LC_2027>0</LC_2027><EP_MYR_2027>0</EP_MYR_2027><E_2028>0</E_2028><LC_2028>0</LC_2028><EP_MYR_2028>0</EP_MYR_2028><E_2029>0</E_2029><LC_2029>0</LC_2029><EP_MYR_2029>0</EP_MYR_2029><E_2030>0</E_2030><LC_2030>0</LC_2030><EP_MYR_2030>0</EP_MYR_2030><E_2031>0</E_2031><LC_2031>0</LC_2031><EP_MYR_2031>0</EP_MYR_2031><E_2032>0</E_2032><LC_2032>0</LC_2032><EP_MYR_2032>0</EP_MYR_2032><E_2033>0</E_2033><LC_2033>0</LC_2033><EP_MYR_2033>0</EP_MYR_2033><E_2034>0</E_2034><LC_2034>0</LC_2034><EP_MYR_2034>0</EP_MYR_2034><E_2035>0</E_2035><LC_2035>0</LC_2035><EP_MYR_2035>0</EP_MYR_2035><E_2036>0</E_2036><LC_2036>0</LC_2036><EP_MYR_2036>0</EP_MYR_2036><E_2037>0</E_2037><LC_2037>0</LC_2037><EP_MYR_2037>0</EP_MYR_2037><E_2038>0</E_2038><LC_2038>0</LC_2038><EP_MYR_2038>0</EP_MYR_2038><E_2039>0</E_2039><LC_2039>0</LC_2039><EP_MYR_2039>0</EP_MYR_2039><E_2040>0</E_2040><LC_2040>0</LC_2040><EP_MYR_2040>0</EP_MYR_2040><E_2041>0</E_2041><LC_2041>0</LC_2041><EP_MYR_2041>0</EP_MYR_2041><E_2042>0</E_2042><LC_2042>0</LC_2042><EP_MYR_2042>0</EP_MYR_2042><E_2043>0</E_2043><LC_2043>0</LC_2043><EP_MYR_2043>0</EP_MYR_2043><E_2044>0</E_2044><LC_2044>0</LC_2044><EP_MYR_2044>0</EP_MYR_2044><E_2045>0</E_2045><LC_2045>0</LC_2045><EP_MYR_2045>0</EP_MYR_2045><sid>1</sid></row><row><id>5</id><E_2012>0</E_2012><LC_2012>0</LC_2012><EP_MYR_2012>0</EP_MYR_2012><E_2013>0</E_2013><LC_2013>0</LC_2013><EP_MYR_2013>0</EP_MYR_2013><E_2014>0</E_2014><LC_2014>0</LC_2014><EP_MYR_2014>0</EP_MYR_2014><E_2015>0</E_2015><LC_2015>0</LC_2015><EP_MYR_2015>0</EP_MYR_2015><E_2016>0</E_2016><LC_2016>0</LC_2016><EP_MYR_2016>0</EP_MYR_2016><E_2017>0</E_2017><LC_2017>0</LC_2017><EP_MYR_2017>0</EP_MYR_2017><E_2018>0</E_2018><LC_2018>0</LC_2018><EP_MYR_2018>0</EP_MYR_2018><E_2019>0</E_2019><LC_2019>0</LC_2019><EP_MYR_2019>0</EP_MYR_2019><E_2020>0</E_2020><LC_2020>0</LC_2020><EP_MYR_2020>0</EP_MYR_2020><E_2021>0</E_2021><LC_2021>0</LC_2021><EP_MYR_2021>0</EP_MYR_2021><E_2022>0</E_2022><LC_2022>0</LC_2022><EP_MYR_2022>0</EP_MYR_2022><E_2023>0</E_2023><LC_2023>0</LC_2023><EP_MYR_2023>0</EP_MYR_2023><E_2024>0</E_2024><LC_2024>0</LC_2024><EP_MYR_2024>0</EP_MYR_2024><E_2025>0</E_2025><LC_2025>0</LC_2025><EP_MYR_2025>0</EP_MYR_2025><E_2026>0</E_2026><LC_2026>0</LC_2026><EP_MYR_2026>0</EP_MYR_2026><E_2027>0</E_2027><LC_2027>0</LC_2027><EP_MYR_2027>0</EP_MYR_2027><E_2028>0</E_2028><LC_2028>0</LC_2028><EP_MYR_2028>0</EP_MYR_2028><E_2029>0</E_2029><LC_2029>0</LC_2029><EP_MYR_2029>0</EP_MYR_2029><E_2030>0</E_2030><LC_2030>0</LC_2030><EP_MYR_2030>0</EP_MYR_2030><E_2031>0</E_2031><LC_2031>0</LC_2031><EP_MYR_2031>0</EP_MYR_2031><E_2032>0</E_2032><LC_2032>0</LC_2032><EP_MYR_2032>0</EP_MYR_2032><E_2033>0</E_2033><LC_2033>0</LC_2033><EP_MYR_2033>0</EP_MYR_2033><E_2034>0</E_2034><LC_2034>0</LC_2034><EP_MYR_2034>0</EP_MYR_2034><E_2035>0</E_2035><LC_2035>0</LC_2035><EP_MYR_2035>0</EP_MYR_2035><E_2036>0</E_2036><LC_2036>0</LC_2036><EP_MYR_2036>0</EP_MYR_2036><E_2037>0</E_2037><LC_2037>0</LC_2037><EP_MYR_2037>0</EP_MYR_2037><E_2038>0</E_2038><LC_2038>0</LC_2038><EP_MYR_2038>0</EP_MYR_2038><E_2039>0</E_2039><LC_2039>0</LC_2039><EP_MYR_2039>0</EP_MYR_2039><E_2040>0</E_2040><LC_2040>0</LC_2040><EP_MYR_2040>0</EP_MYR_2040><E_2041>0</E_2041><LC_2041>0</LC_2041><EP_MYR_2041>0</EP_MYR_2041><E_2042>0</E_2042><LC_2042>0</LC_2042><EP_MYR_2042>0</EP_MYR_2042><E_2043>0</E_2043><LC_2043>0</LC_2043><EP_MYR_2043>0</EP_MYR_2043><E_2044>0</E_2044><LC_2044>0</LC_2044><EP_MYR_2044>0</EP_MYR_2044><E_2045>0</E_2045><LC_2045>0</LC_2045><EP_MYR_2045>0</EP_MYR_2045><sid>1</sid></row><row><id>6</id><E_2012>0</E_2012><LC_2012>0</LC_2012><EP_MYR_2012>0</EP_MYR_2012><E_2013>0</E_2013><LC_2013>0</LC_2013><EP_MYR_2013>0</EP_MYR_2013><E_2014>0</E_2014><LC_2014>0</LC_2014><EP_MYR_2014>0</EP_MYR_2014><E_2015>0</E_2015><LC_2015>0</LC_2015><EP_MYR_2015>0</EP_MYR_2015><E_2016>0</E_2016><LC_2016>0</LC_2016><EP_MYR_2016>0</EP_MYR_2016><E_2017>0</E_2017><LC_2017>0</LC_2017><EP_MYR_2017>0</EP_MYR_2017><E_2018>0</E_2018><LC_2018>0</LC_2018><EP_MYR_2018>0</EP_MYR_2018><E_2019>0</E_2019><LC_2019>0</LC_2019><EP_MYR_2019>0</EP_MYR_2019><E_2020>0</E_2020><LC_2020>0</LC_2020><EP_MYR_2020>0</EP_MYR_2020><E_2021>0</E_2021><LC_2021>0</LC_2021><EP_MYR_2021>0</EP_MYR_2021><E_2022>0</E_2022><LC_2022>0</LC_2022><EP_MYR_2022>0</EP_MYR_2022><E_2023>0</E_2023><LC_2023>0</LC_2023><EP_MYR_2023>0</EP_MYR_2023><E_2024>0</E_2024><LC_2024>0</LC_2024><EP_MYR_2024>0</EP_MYR_2024><E_2025>0</E_2025><LC_2025>0</LC_2025><EP_MYR_2025>0</EP_MYR_2025><E_2026>0</E_2026><LC_2026>0</LC_2026><EP_MYR_2026>0</EP_MYR_2026><E_2027>0</E_2027><LC_2027>0</LC_2027><EP_MYR_2027>0</EP_MYR_2027><E_2028>0</E_2028><LC_2028>0</LC_2028><EP_MYR_2028>0</EP_MYR_2028><E_2029>0</E_2029><LC_2029>0</LC_2029><EP_MYR_2029>0</EP_MYR_2029><E_2030>0</E_2030><LC_2030>0</LC_2030><EP_MYR_2030>0</EP_MYR_2030><E_2031>0</E_2031><LC_2031>0</LC_2031><EP_MYR_2031>0</EP_MYR_2031><E_2032>0</E_2032><LC_2032>0</LC_2032><EP_MYR_2032>0</EP_MYR_2032><E_2033>0</E_2033><LC_2033>0</LC_2033><EP_MYR_2033>0</EP_MYR_2033><E_2034>0</E_2034><LC_2034>0</LC_2034><EP_MYR_2034>0</EP_MYR_2034><E_2035>0</E_2035><LC_2035>0</LC_2035><EP_MYR_2035>0</EP_MYR_2035><E_2036>0</E_2036><LC_2036>0</LC_2036><EP_MYR_2036>0</EP_MYR_2036><E_2037>0</E_2037><LC_2037>0</LC_2037><EP_MYR_2037>0</EP_MYR_2037><E_2038>0</E_2038><LC_2038>0</LC_2038><EP_MYR_2038>0</EP_MYR_2038><E_2039>0</E_2039><LC_2039>0</LC_2039><EP_MYR_2039>0</EP_MYR_2039><E_2040>0</E_2040><LC_2040>0</LC_2040><EP_MYR_2040>0</EP_MYR_2040><E_2041>0</E_2041><LC_2041>0</LC_2041><EP_MYR_2041>0</EP_MYR_2041><E_2042>0</E_2042><LC_2042>0</LC_2042><EP_MYR_2042>0</EP_MYR_2042><E_2043>0</E_2043><LC_2043>0</LC_2043><EP_MYR_2043>0</EP_MYR_2043><E_2044>0</E_2044><LC_2044>0</LC_2044><EP_MYR_2044>0</EP_MYR_2044><E_2045>0</E_2045><LC_2045>0</LC_2045><EP_MYR_2045>0</EP_MYR_2045><sid>1</sid></row><row><id>7</id><E_2012>0</E_2012><LC_2012>0</LC_2012><EP_MYR_2012>0</EP_MYR_2012><E_2013>0</E_2013><LC_2013>0</LC_2013><EP_MYR_2013>0</EP_MYR_2013><E_2014>0</E_2014><LC_2014>0</LC_2014><EP_MYR_2014>0</EP_MYR_2014><E_2015>0</E_2015><LC_2015>0</LC_2015><EP_MYR_2015>0</EP_MYR_2015><E_2016>0</E_2016><LC_2016>0</LC_2016><EP_MYR_2016>0</EP_MYR_2016><E_2017>0</E_2017><LC_2017>0</LC_2017><EP_MYR_2017>0</EP_MYR_2017><E_2018>0</E_2018><LC_2018>0</LC_2018><EP_MYR_2018>0</EP_MYR_2018><E_2019>0</E_2019><LC_2019>0</LC_2019><EP_MYR_2019>0</EP_MYR_2019><E_2020>0</E_2020><LC_2020>0</LC_2020><EP_MYR_2020>0</EP_MYR_2020><E_2021>0</E_2021><LC_2021>0</LC_2021><EP_MYR_2021>0</EP_MYR_2021><E_2022>0</E_2022><LC_2022>0</LC_2022><EP_MYR_2022>0</EP_MYR_2022><E_2023>0</E_2023><LC_2023>0</LC_2023><EP_MYR_2023>0</EP_MYR_2023><E_2024>0</E_2024><LC_2024>0</LC_2024><EP_MYR_2024>0</EP_MYR_2024><E_2025>0</E_2025><LC_2025>0</LC_2025><EP_MYR_2025>0</EP_MYR_2025><E_2026>0</E_2026><LC_2026>0</LC_2026><EP_MYR_2026>0</EP_MYR_2026><E_2027>0</E_2027><LC_2027>0</LC_2027><EP_MYR_2027>0</EP_MYR_2027><E_2028>0</E_2028><LC_2028>0</LC_2028><EP_MYR_2028>0</EP_MYR_2028><E_2029>0</E_2029><LC_2029>0</LC_2029><EP_MYR_2029>0</EP_MYR_2029><E_2030>0</E_2030><LC_2030>0</LC_2030><EP_MYR_2030>0</EP_MYR_2030><E_2031>0</E_2031><LC_2031>0</LC_2031><EP_MYR_2031>0</EP_MYR_2031><E_2032>0</E_2032><LC_2032>0</LC_2032><EP_MYR_2032>0</EP_MYR_2032><E_2033>0</E_2033><LC_2033>0</LC_2033><EP_MYR_2033>0</EP_MYR_2033><E_2034>0</E_2034><LC_2034>0</LC_2034><EP_MYR_2034>0</EP_MYR_2034><E_2035>0</E_2035><LC_2035>0</LC_2035><EP_MYR_2035>0</EP_MYR_2035><E_2036>0</E_2036><LC_2036>0</LC_2036><EP_MYR_2036>0</EP_MYR_2036><E_2037>0</E_2037><LC_2037>0</LC_2037><EP_MYR_2037>0</EP_MYR_2037><E_2038>0</E_2038><LC_2038>0</LC_2038><EP_MYR_2038>0</EP_MYR_2038><E_2039>0</E_2039><LC_2039>0</LC_2039><EP_MYR_2039>0</EP_MYR_2039><E_2040>0</E_2040><LC_2040>0</LC_2040><EP_MYR_2040>0</EP_MYR_2040><E_2041>0</E_2041><LC_2041>0</LC_2041><EP_MYR_2041>0</EP_MYR_2041><E_2042>0</E_2042><LC_2042>0</LC_2042><EP_MYR_2042>0</EP_MYR_2042><E_2043>0</E_2043><LC_2043>0</LC_2043><EP_MYR_2043>0</EP_MYR_2043><E_2044>0</E_2044><LC_2044>0</LC_2044><EP_MYR_2044>0</EP_MYR_2044><E_2045>0</E_2045><LC_2045>0</LC_2045><EP_MYR_2045>0</EP_MYR_2045><sid>1</sid></row><row><id>8</id><E_2012>0</E_2012><LC_2012>0</LC_2012><EP_MYR_2012>0</EP_MYR_2012><E_2013>0</E_2013><LC_2013>0</LC_2013><EP_MYR_2013>0</EP_MYR_2013><E_2014>0</E_2014><LC_2014>0</LC_2014><EP_MYR_2014>0</EP_MYR_2014><E_2015>0</E_2015><LC_2015>0</LC_2015><EP_MYR_2015>0</EP_MYR_2015><E_2016>0</E_2016><LC_2016>0</LC_2016><EP_MYR_2016>0</EP_MYR_2016><E_2017>0</E_2017><LC_2017>0</LC_2017><EP_MYR_2017>0</EP_MYR_2017><E_2018>0</E_2018><LC_2018>0</LC_2018><EP_MYR_2018>0</EP_MYR_2018><E_2019>0</E_2019><LC_2019>0</LC_2019><EP_MYR_2019>0</EP_MYR_2019><E_2020>0</E_2020><LC_2020>0</LC_2020><EP_MYR_2020>0</EP_MYR_2020><E_2021>0</E_2021><LC_2021>0</LC_2021><EP_MYR_2021>0</EP_MYR_2021><E_2022>0</E_2022><LC_2022>0</LC_2022><EP_MYR_2022>0</EP_MYR_2022><E_2023>0</E_2023><LC_2023>0</LC_2023><EP_MYR_2023>0</EP_MYR_2023><E_2024>0</E_2024><LC_2024>0</LC_2024><EP_MYR_2024>0</EP_MYR_2024><E_2025>0</E_2025><LC_2025>0</LC_2025><EP_MYR_2025>0</EP_MYR_2025><E_2026>0</E_2026><LC_2026>0</LC_2026><EP_MYR_2026>0</EP_MYR_2026><E_2027>0</E_2027><LC_2027>0</LC_2027><EP_MYR_2027>0</EP_MYR_2027><E_2028>0</E_2028><LC_2028>0</LC_2028><EP_MYR_2028>0</EP_MYR_2028><E_2029>0</E_2029><LC_2029>0</LC_2029><EP_MYR_2029>0</EP_MYR_2029><E_2030>0</E_2030><LC_2030>0</LC_2030><EP_MYR_2030>0</EP_MYR_2030><E_2031>0</E_2031><LC_2031>0</LC_2031><EP_MYR_2031>0</EP_MYR_2031><E_2032>0</E_2032><LC_2032>0</LC_2032><EP_MYR_2032>0</EP_MYR_2032><E_2033>0</E_2033><LC_2033>0</LC_2033><EP_MYR_2033>0</EP_MYR_2033><E_2034>0</E_2034><LC_2034>0</LC_2034><EP_MYR_2034>0</EP_MYR_2034><E_2035>0</E_2035><LC_2035>0</LC_2035><EP_MYR_2035>0</EP_MYR_2035><E_2036>0</E_2036><LC_2036>0</LC_2036><EP_MYR_2036>0</EP_MYR_2036><E_2037>0</E_2037><LC_2037>0</LC_2037><EP_MYR_2037>0</EP_MYR_2037><E_2038>0</E_2038><LC_2038>0</LC_2038><EP_MYR_2038>0</EP_MYR_2038><E_2039>0</E_2039><LC_2039>0</LC_2039><EP_MYR_2039>0</EP_MYR_2039><E_2040>0</E_2040><LC_2040>0</LC_2040><EP_MYR_2040>0</EP_MYR_2040><E_2041>0</E_2041><LC_2041>0</LC_2041><EP_MYR_2041>0</EP_MYR_2041><E_2042>0</E_2042><LC_2042>0</LC_2042><EP_MYR_2042>0</EP_MYR_2042><E_2043>0</E_2043><LC_2043>0</LC_2043><EP_MYR_2043>0</EP_MYR_2043><E_2044>0</E_2044><LC_2044>0</LC_2044><EP_MYR_2044>0</EP_MYR_2044><E_2045>0</E_2045><LC_2045>0</LC_2045><EP_MYR_2045>0</EP_MYR_2045><sid>1</sid></row><row><id>9</id><E_2012>0</E_2012><LC_2012>0</LC_2012><EP_MYR_2012>0</EP_MYR_2012><E_2013>0</E_2013><LC_2013>0</LC_2013><EP_MYR_2013>0</EP_MYR_2013><E_2014>0</E_2014><LC_2014>0</LC_2014><EP_MYR_2014>0</EP_MYR_2014><E_2015>0</E_2015><LC_2015>0</LC_2015><EP_MYR_2015>0</EP_MYR_2015><E_2016>0</E_2016><LC_2016>0</LC_2016><EP_MYR_2016>0</EP_MYR_2016><E_2017>0</E_2017><LC_2017>0</LC_2017><EP_MYR_2017>0</EP_MYR_2017><E_2018>0</E_2018><LC_2018>0</LC_2018><EP_MYR_2018>0</EP_MYR_2018><E_2019>0</E_2019><LC_2019>0</LC_2019><EP_MYR_2019>0</EP_MYR_2019><E_2020>0</E_2020><LC_2020>0</LC_2020><EP_MYR_2020>0</EP_MYR_2020><E_2021>0</E_2021><LC_2021>0</LC_2021><EP_MYR_2021>0</EP_MYR_2021><E_2022>0</E_2022><LC_2022>0</LC_2022><EP_MYR_2022>0</EP_MYR_2022><E_2023>0</E_2023><LC_2023>0</LC_2023><EP_MYR_2023>0</EP_MYR_2023><E_2024>0</E_2024><LC_2024>0</LC_2024><EP_MYR_2024>0</EP_MYR_2024><E_2025>0</E_2025><LC_2025>0</LC_2025><EP_MYR_2025>0</EP_MYR_2025><E_2026>0</E_2026><LC_2026>0</LC_2026><EP_MYR_2026>0</EP_MYR_2026><E_2027>0</E_2027><LC_2027>0</LC_2027><EP_MYR_2027>0</EP_MYR_2027><E_2028>0</E_2028><LC_2028>0</LC_2028><EP_MYR_2028>0</EP_MYR_2028><E_2029>0</E_2029><LC_2029>0</LC_2029><EP_MYR_2029>0</EP_MYR_2029><E_2030>0</E_2030><LC_2030>0</LC_2030><EP_MYR_2030>0</EP_MYR_2030><E_2031>0</E_2031><LC_2031>0</LC_2031><EP_MYR_2031>0</EP_MYR_2031><E_2032>0</E_2032><LC_2032>0</LC_2032><EP_MYR_2032>0</EP_MYR_2032><E_2033>0</E_2033><LC_2033>0</LC_2033><EP_MYR_2033>0</EP_MYR_2033><E_2034>0</E_2034><LC_2034>0</LC_2034><EP_MYR_2034>0</EP_MYR_2034><E_2035>0</E_2035><LC_2035>0</LC_2035><EP_MYR_2035>0</EP_MYR_2035><E_2036>0</E_2036><LC_2036>0</LC_2036><EP_MYR_2036>0</EP_MYR_2036><E_2037>0</E_2037><LC_2037>0</LC_2037><EP_MYR_2037>0</EP_MYR_2037><E_2038>0</E_2038><LC_2038>0</LC_2038><EP_MYR_2038>0</EP_MYR_2038><E_2039>0</E_2039><LC_2039>0</LC_2039><EP_MYR_2039>0</EP_MYR_2039><E_2040>0</E_2040><LC_2040>0</LC_2040><EP_MYR_2040>0</EP_MYR_2040><E_2041>0</E_2041><LC_2041>0</LC_2041><EP_MYR_2041>0</EP_MYR_2041><E_2042>0</E_2042><LC_2042>0</LC_2042><EP_MYR_2042>0</EP_MYR_2042><E_2043>0</E_2043><LC_2043>0</LC_2043><EP_MYR_2043>0</EP_MYR_2043><E_2044>0</E_2044><LC_2044>0</LC_2044><EP_MYR_2044>0</EP_MYR_2044><E_2045>0</E_2045><LC_2045>0</LC_2045><EP_MYR_2045>0</EP_MYR_2045><sid>1</sid></row><row><id>10</id><E_2012>0</E_2012><LC_2012>0</LC_2012><EP_MYR_2012>0</EP_MYR_2012><E_2013>0</E_2013><LC_2013>0</LC_2013><EP_MYR_2013>0</EP_MYR_2013><E_2014>0</E_2014><LC_2014>0</LC_2014><EP_MYR_2014>0</EP_MYR_2014><E_2015>0</E_2015><LC_2015>0</LC_2015><EP_MYR_2015>0</EP_MYR_2015><E_2016>0</E_2016><LC_2016>0</LC_2016><EP_MYR_2016>0</EP_MYR_2016><E_2017>0</E_2017><LC_2017>0</LC_2017><EP_MYR_2017>0</EP_MYR_2017><E_2018>0</E_2018><LC_2018>0</LC_2018><EP_MYR_2018>0</EP_MYR_2018><E_2019>0</E_2019><LC_2019>0</LC_2019><EP_MYR_2019>0</EP_MYR_2019><E_2020>0</E_2020><LC_2020>0</LC_2020><EP_MYR_2020>0</EP_MYR_2020><E_2021>0</E_2021><LC_2021>0</LC_2021><EP_MYR_2021>0</EP_MYR_2021><E_2022>0</E_2022><LC_2022>0</LC_2022><EP_MYR_2022>0</EP_MYR_2022><E_2023>0</E_2023><LC_2023>0</LC_2023><EP_MYR_2023>0</EP_MYR_2023><E_2024>0</E_2024><LC_2024>0</LC_2024><EP_MYR_2024>0</EP_MYR_2024><E_2025>0</E_2025><LC_2025>0</LC_2025><EP_MYR_2025>0</EP_MYR_2025><E_2026>0</E_2026><LC_2026>0</LC_2026><EP_MYR_2026>0</EP_MYR_2026><E_2027>0</E_2027><LC_2027>0</LC_2027><EP_MYR_2027>0</EP_MYR_2027><E_2028>0</E_2028><LC_2028>0</LC_2028><EP_MYR_2028>0</EP_MYR_2028><E_2029>0</E_2029><LC_2029>0</LC_2029><EP_MYR_2029>0</EP_MYR_2029><E_2030>0</E_2030><LC_2030>0</LC_2030><EP_MYR_2030>0</EP_MYR_2030><E_2031>0</E_2031><LC_2031>0</LC_2031><EP_MYR_2031>0</EP_MYR_2031><E_2032>0</E_2032><LC_2032>0</LC_2032><EP_MYR_2032>0</EP_MYR_2032><E_2033>0</E_2033><LC_2033>0</LC_2033><EP_MYR_2033>0</EP_MYR_2033><E_2034>0</E_2034><LC_2034>0</LC_2034><EP_MYR_2034>0</EP_MYR_2034><E_2035>0</E_2035><LC_2035>0</LC_2035><EP_MYR_2035>0</EP_MYR_2035><E_2036>0</E_2036><LC_2036>0</LC_2036><EP_MYR_2036>0</EP_MYR_2036><E_2037>0</E_2037><LC_2037>0</LC_2037><EP_MYR_2037>0</EP_MYR_2037><E_2038>0</E_2038><LC_2038>0</LC_2038><EP_MYR_2038>0</EP_MYR_2038><E_2039>0</E_2039><LC_2039>0</LC_2039><EP_MYR_2039>0</EP_MYR_2039><E_2040>0</E_2040><LC_2040>0</LC_2040><EP_MYR_2040>0</EP_MYR_2040><E_2041>0</E_2041><LC_2041>0</LC_2041><EP_MYR_2041>0</EP_MYR_2041><E_2042>0</E_2042><LC_2042>0</LC_2042><EP_MYR_2042>0</EP_MYR_2042><E_2043>0</E_2043><LC_2043>0</LC_2043><EP_MYR_2043>0</EP_MYR_2043><E_2044>0</E_2044><LC_2044>0</LC_2044><EP_MYR_2044>0</EP_MYR_2044><E_2045>0</E_2045><LC_2045>0</LC_2045><EP_MYR_2045>0</EP_MYR_2045><sid>1</sid></row><row><id>11</id><E_2012>0</E_2012><LC_2012>0</LC_2012><EP_MYR_2012>0</EP_MYR_2012><E_2013>0</E_2013><LC_2013>0</LC_2013><EP_MYR_2013>0</EP_MYR_2013><E_2014>0</E_2014><LC_2014>0</LC_2014><EP_MYR_2014>0</EP_MYR_2014><E_2015>0</E_2015><LC_2015>0</LC_2015><EP_MYR_2015>0</EP_MYR_2015><E_2016>0</E_2016><LC_2016>0</LC_2016><EP_MYR_2016>0</EP_MYR_2016><E_2017>0</E_2017><LC_2017>0</LC_2017><EP_MYR_2017>0</EP_MYR_2017><E_2018>0</E_2018><LC_2018>0</LC_2018><EP_MYR_2018>0</EP_MYR_2018><E_2019>0</E_2019><LC_2019>0</LC_2019><EP_MYR_2019>0</EP_MYR_2019><E_2020>0</E_2020><LC_2020>0</LC_2020><EP_MYR_2020>0</EP_MYR_2020><E_2021>0</E_2021><LC_2021>0</LC_2021><EP_MYR_2021>0</EP_MYR_2021><E_2022>0</E_2022><LC_2022>0</LC_2022><EP_MYR_2022>0</EP_MYR_2022><E_2023>0</E_2023><LC_2023>0</LC_2023><EP_MYR_2023>0</EP_MYR_2023><E_2024>0</E_2024><LC_2024>0</LC_2024><EP_MYR_2024>0</EP_MYR_2024><E_2025>0</E_2025><LC_2025>0</LC_2025><EP_MYR_2025>0</EP_MYR_2025><E_2026>0</E_2026><LC_2026>0</LC_2026><EP_MYR_2026>0</EP_MYR_2026><E_2027>0</E_2027><LC_2027>0</LC_2027><EP_MYR_2027>0</EP_MYR_2027><E_2028>0</E_2028><LC_2028>0</LC_2028><EP_MYR_2028>0</EP_MYR_2028><E_2029>0</E_2029><LC_2029>0</LC_2029><EP_MYR_2029>0</EP_MYR_2029><E_2030>0</E_2030><LC_2030>0</LC_2030><EP_MYR_2030>0</EP_MYR_2030><E_2031>0</E_2031><LC_2031>0</LC_2031><EP_MYR_2031>0</EP_MYR_2031><E_2032>0</E_2032><LC_2032>0</LC_2032><EP_MYR_2032>0</EP_MYR_2032><E_2033>0</E_2033><LC_2033>0</LC_2033><EP_MYR_2033>0</EP_MYR_2033><E_2034>0</E_2034><LC_2034>0</LC_2034><EP_MYR_2034>0</EP_MYR_2034><E_2035>0</E_2035><LC_2035>0</LC_2035><EP_MYR_2035>0</EP_MYR_2035><E_2036>0</E_2036><LC_2036>0</LC_2036><EP_MYR_2036>0</EP_MYR_2036><E_2037>0</E_2037><LC_2037>0</LC_2037><EP_MYR_2037>0</EP_MYR_2037><E_2038>0</E_2038><LC_2038>0</LC_2038><EP_MYR_2038>0</EP_MYR_2038><E_2039>0</E_2039><LC_2039>0</LC_2039><EP_MYR_2039>0</EP_MYR_2039><E_2040>0</E_2040><LC_2040>0</LC_2040><EP_MYR_2040>0</EP_MYR_2040><E_2041>0</E_2041><LC_2041>0</LC_2041><EP_MYR_2041>0</EP_MYR_2041><E_2042>0</E_2042><LC_2042>0</LC_2042><EP_MYR_2042>0</EP_MYR_2042><E_2043>0</E_2043><LC_2043>0</LC_2043><EP_MYR_2043>0</EP_MYR_2043><E_2044>0</E_2044><LC_2044>0</LC_2044><EP_MYR_2044>0</EP_MYR_2044><E_2045>0</E_2045><LC_2045>0</LC_2045><EP_MYR_2045>0</EP_MYR_2045><sid>1</sid></row><row><id>12</id><E_2012>0</E_2012><LC_2012>0</LC_2012><EP_MYR_2012>0</EP_MYR_2012><E_2013>0</E_2013><LC_2013>0</LC_2013><EP_MYR_2013>0</EP_MYR_2013><E_2014>0</E_2014><LC_2014>0</LC_2014><EP_MYR_2014>0</EP_MYR_2014><E_2015>0</E_2015><LC_2015>0</LC_2015><EP_MYR_2015>0</EP_MYR_2015><E_2016>0</E_2016><LC_2016>0</LC_2016><EP_MYR_2016>0</EP_MYR_2016><E_2017>0</E_2017><LC_2017>0</LC_2017><EP_MYR_2017>0</EP_MYR_2017><E_2018>0</E_2018><LC_2018>0</LC_2018><EP_MYR_2018>0</EP_MYR_2018><E_2019>0</E_2019><LC_2019>0</LC_2019><EP_MYR_2019>0</EP_MYR_2019><E_2020>0</E_2020><LC_2020>0</LC_2020><EP_MYR_2020>0</EP_MYR_2020><E_2021>0</E_2021><LC_2021>0</LC_2021><EP_MYR_2021>0</EP_MYR_2021><E_2022>0</E_2022><LC_2022>0</LC_2022><EP_MYR_2022>0</EP_MYR_2022><E_2023>0</E_2023><LC_2023>0</LC_2023><EP_MYR_2023>0</EP_MYR_2023><E_2024>0</E_2024><LC_2024>0</LC_2024><EP_MYR_2024>0</EP_MYR_2024><E_2025>0</E_2025><LC_2025>0</LC_2025><EP_MYR_2025>0</EP_MYR_2025><E_2026>0</E_2026><LC_2026>0</LC_2026><EP_MYR_2026>0</EP_MYR_2026><E_2027>0</E_2027><LC_2027>0</LC_2027><EP_MYR_2027>0</EP_MYR_2027><E_2028>0</E_2028><LC_2028>0</LC_2028><EP_MYR_2028>0</EP_MYR_2028><E_2029>0</E_2029><LC_2029>0</LC_2029><EP_MYR_2029>0</EP_MYR_2029><E_2030>0</E_2030><LC_2030>0</LC_2030><EP_MYR_2030>0</EP_MYR_2030><E_2031>0</E_2031><LC_2031>0</LC_2031><EP_MYR_2031>0</EP_MYR_2031><E_2032>0</E_2032><LC_2032>0</LC_2032><EP_MYR_2032>0</EP_MYR_2032><E_2033>0</E_2033><LC_2033>0</LC_2033><EP_MYR_2033>0</EP_MYR_2033><E_2034>0</E_2034><LC_2034>0</LC_2034><EP_MYR_2034>0</EP_MYR_2034><E_2035>0</E_2035><LC_2035>0</LC_2035><EP_MYR_2035>0</EP_MYR_2035><E_2036>0</E_2036><LC_2036>0</LC_2036><EP_MYR_2036>0</EP_MYR_2036><E_2037>0</E_2037><LC_2037>0</LC_2037><EP_MYR_2037>0</EP_MYR_2037><E_2038>0</E_2038><LC_2038>0</LC_2038><EP_MYR_2038>0</EP_MYR_2038><E_2039>0</E_2039><LC_2039>0</LC_2039><EP_MYR_2039>0</EP_MYR_2039><E_2040>0</E_2040><LC_2040>0</LC_2040><EP_MYR_2040>0</EP_MYR_2040><E_2041>0</E_2041><LC_2041>0</LC_2041><EP_MYR_2041>0</EP_MYR_2041><E_2042>0</E_2042><LC_2042>0</LC_2042><EP_MYR_2042>0</EP_MYR_2042><E_2043>0</E_2043><LC_2043>0</LC_2043><EP_MYR_2043>0</EP_MYR_2043><E_2044>0</E_2044><LC_2044>0</LC_2044><EP_MYR_2044>0</EP_MYR_2044><E_2045>0</E_2045><LC_2045>0</LC_2045><EP_MYR_2045>0</EP_MYR_2045><sid>1</sid></row></data></cal_totalpurchase>
