<?xml version="1.0" encoding="utf-8"?>
<cal_depreciation><meta><autoIncrement>2</autoIncrement></meta><data><row><id>1</id><pid>1</pid><D_2017>218.73436655616</D_2017><D_2018>131.2406199337</D_2018><D_2019>78.744371960218</D_2019><D_2020>47.246623176131</D_2020><D_2021>28.347973905678</D_2021><D_2022>17.008784343407</D_2022><D_2023>10.205270606044</D_2023><D_2024>6.1231623636265</D_2024><D_2025>4.5923717727199</D_2025><D_2026>4.5923717727199</D_2026></row><row><id>2</id><TN_2012>0</TN_2012><TN_2013>0</TN_2013><TN_2014>0</TN_2014><TN_2015>0</TN_2015><TN_2016>0</TN_2016><TN_2017>218.73436655616</TN_2017><TN_2018>131.2406199337</TN_2018><TN_2019>78.744371960218</TN_2019><TN_2020>47.246623176131</TN_2020><TN_2021>28.347973905678</TN_2021><TN_2022>17.008784343407</TN_2022><TN_2023>10.205270606044</TN_2023><TN_2024>6.1231623636265</TN_2024><TN_2025>4.5923717727199</TN_2025><TN_2026>4.5923717727199</TN_2026><TN_2027>0</TN_2027><TN_2028>0</TN_2028><TN_2029>0</TN_2029><TN_2030>0</TN_2030><TN_2031>0</TN_2031><TN_2032>0</TN_2032><TN_2033>0</TN_2033><TN_2034>0</TN_2034><TN_2035>0</TN_2035><TN_2036>0</TN_2036><TN_2037>0</TN_2037><TN_2038>0</TN_2038><TN_2039>0</TN_2039><TN_2040>0</TN_2040><TN_2041>0</TN_2041><TN_2042>0</TN_2042><TN_2043>0</TN_2043><TN_2044>0</TN_2044><TN_2045>0</TN_2045><sid>1</sid><T_2012>0</T_2012><T_2013>0</T_2013><T_2014>0</T_2014><T_2015>0</T_2015><T_2016>0</T_2016><T_2017>218.73436655616</T_2017><T_2018>131.2406199337</T_2018><T_2019>78.744371960218</T_2019><T_2020>47.246623176131</T_2020><T_2021>28.347973905678</T_2021><T_2022>17.008784343407</T_2022><T_2023>10.205270606044</T_2023><T_2024>6.1231623636265</T_2024><T_2025>4.5923717727199</T_2025><T_2026>4.5923717727199</T_2026><T_2027>0</T_2027><T_2028>0</T_2028><T_2029>0</T_2029><T_2030>0</T_2030><T_2031>0</T_2031><T_2032>0</T_2032><T_2033>0</T_2033><T_2034>0</T_2034><T_2035>0</T_2035><T_2036>0</T_2036><T_2037>0</T_2037><T_2038>0</T_2038><T_2039>0</T_2039><T_2040>0</T_2040><T_2041>0</T_2041><T_2042>0</T_2042><T_2043>0</T_2043><T_2044>0</T_2044><T_2045>0</T_2045></row></data></cal_depreciation>
